[
  {
    "name": "西村集_page4",
    "url": "集藏/四库别集/西村集_page4.html"
  },
  {
    "name": "西村集_page5",
    "url": "集藏/四库别集/西村集_page5.html"
  },
  {
    "name": "西村集_page6",
    "url": "集藏/四库别集/西村集_page6.html"
  },
  {
    "name": "西村集_page7",
    "url": "集藏/四库别集/西村集_page7.html"
  },
  {
    "name": "西村集_page8",
    "url": "集藏/四库别集/西村集_page8.html"
  },
  {
    "name": "西村集_page9",
    "url": "集藏/四库别集/西村集_page9.html"
  },
  {
    "name": "西河集_page1",
    "url": "集藏/四库别集/西河集_page1.html"
  },
  {
    "name": "西河集_page10",
    "url": "集藏/四库别集/西河集_page10.html"
  },
  {
    "name": "西河集_page100",
    "url": "集藏/四库别集/西河集_page100.html"
  },
  {
    "name": "西河集_page101",
    "url": "集藏/四库别集/西河集_page101.html"
  },
  {
    "name": "西河集_page102",
    "url": "集藏/四库别集/西河集_page102.html"
  },
  {
    "name": "西河集_page103",
    "url": "集藏/四库别集/西河集_page103.html"
  },
  {
    "name": "西河集_page104",
    "url": "集藏/四库别集/西河集_page104.html"
  },
  {
    "name": "西河集_page105",
    "url": "集藏/四库别集/西河集_page105.html"
  },
  {
    "name": "西河集_page106",
    "url": "集藏/四库别集/西河集_page106.html"
  },
  {
    "name": "西河集_page107",
    "url": "集藏/四库别集/西河集_page107.html"
  },
  {
    "name": "西河集_page108",
    "url": "集藏/四库别集/西河集_page108.html"
  },
  {
    "name": "西河集_page109",
    "url": "集藏/四库别集/西河集_page109.html"
  },
  {
    "name": "西河集_page11",
    "url": "集藏/四库别集/西河集_page11.html"
  },
  {
    "name": "西河集_page110",
    "url": "集藏/四库别集/西河集_page110.html"
  },
  {
    "name": "西河集_page111",
    "url": "集藏/四库别集/西河集_page111.html"
  },
  {
    "name": "西河集_page112",
    "url": "集藏/四库别集/西河集_page112.html"
  },
  {
    "name": "西河集_page113",
    "url": "集藏/四库别集/西河集_page113.html"
  },
  {
    "name": "西河集_page114",
    "url": "集藏/四库别集/西河集_page114.html"
  },
  {
    "name": "西河集_page115",
    "url": "集藏/四库别集/西河集_page115.html"
  },
  {
    "name": "西河集_page116",
    "url": "集藏/四库别集/西河集_page116.html"
  },
  {
    "name": "西河集_page117",
    "url": "集藏/四库别集/西河集_page117.html"
  },
  {
    "name": "西河集_page118",
    "url": "集藏/四库别集/西河集_page118.html"
  },
  {
    "name": "西河集_page119",
    "url": "集藏/四库别集/西河集_page119.html"
  },
  {
    "name": "西河集_page12",
    "url": "集藏/四库别集/西河集_page12.html"
  },
  {
    "name": "西河集_page120",
    "url": "集藏/四库别集/西河集_page120.html"
  },
  {
    "name": "西河集_page121",
    "url": "集藏/四库别集/西河集_page121.html"
  },
  {
    "name": "西河集_page122",
    "url": "集藏/四库别集/西河集_page122.html"
  },
  {
    "name": "西河集_page123",
    "url": "集藏/四库别集/西河集_page123.html"
  },
  {
    "name": "西河集_page124",
    "url": "集藏/四库别集/西河集_page124.html"
  },
  {
    "name": "西河集_page125",
    "url": "集藏/四库别集/西河集_page125.html"
  },
  {
    "name": "西河集_page126",
    "url": "集藏/四库别集/西河集_page126.html"
  },
  {
    "name": "西河集_page127",
    "url": "集藏/四库别集/西河集_page127.html"
  },
  {
    "name": "西河集_page128",
    "url": "集藏/四库别集/西河集_page128.html"
  },
  {
    "name": "西河集_page129",
    "url": "集藏/四库别集/西河集_page129.html"
  },
  {
    "name": "西河集_page13",
    "url": "集藏/四库别集/西河集_page13.html"
  },
  {
    "name": "西河集_page130",
    "url": "集藏/四库别集/西河集_page130.html"
  },
  {
    "name": "西河集_page131",
    "url": "集藏/四库别集/西河集_page131.html"
  },
  {
    "name": "西河集_page132",
    "url": "集藏/四库别集/西河集_page132.html"
  },
  {
    "name": "西河集_page133",
    "url": "集藏/四库别集/西河集_page133.html"
  },
  {
    "name": "西河集_page134",
    "url": "集藏/四库别集/西河集_page134.html"
  },
  {
    "name": "西河集_page135",
    "url": "集藏/四库别集/西河集_page135.html"
  },
  {
    "name": "西河集_page136",
    "url": "集藏/四库别集/西河集_page136.html"
  },
  {
    "name": "西河集_page14",
    "url": "集藏/四库别集/西河集_page14.html"
  },
  {
    "name": "西河集_page15",
    "url": "集藏/四库别集/西河集_page15.html"
  },
  {
    "name": "西河集_page16",
    "url": "集藏/四库别集/西河集_page16.html"
  },
  {
    "name": "西河集_page17",
    "url": "集藏/四库别集/西河集_page17.html"
  },
  {
    "name": "西河集_page18",
    "url": "集藏/四库别集/西河集_page18.html"
  },
  {
    "name": "西河集_page19",
    "url": "集藏/四库别集/西河集_page19.html"
  },
  {
    "name": "西河集_page2",
    "url": "集藏/四库别集/西河集_page2.html"
  },
  {
    "name": "西河集_page20",
    "url": "集藏/四库别集/西河集_page20.html"
  },
  {
    "name": "西河集_page21",
    "url": "集藏/四库别集/西河集_page21.html"
  },
  {
    "name": "西河集_page22",
    "url": "集藏/四库别集/西河集_page22.html"
  },
  {
    "name": "西河集_page23",
    "url": "集藏/四库别集/西河集_page23.html"
  },
  {
    "name": "西河集_page24",
    "url": "集藏/四库别集/西河集_page24.html"
  },
  {
    "name": "西河集_page25",
    "url": "集藏/四库别集/西河集_page25.html"
  },
  {
    "name": "西河集_page26",
    "url": "集藏/四库别集/西河集_page26.html"
  },
  {
    "name": "西河集_page27",
    "url": "集藏/四库别集/西河集_page27.html"
  },
  {
    "name": "西河集_page28",
    "url": "集藏/四库别集/西河集_page28.html"
  },
  {
    "name": "西河集_page29",
    "url": "集藏/四库别集/西河集_page29.html"
  },
  {
    "name": "西河集_page3",
    "url": "集藏/四库别集/西河集_page3.html"
  },
  {
    "name": "西河集_page30",
    "url": "集藏/四库别集/西河集_page30.html"
  },
  {
    "name": "西河集_page31",
    "url": "集藏/四库别集/西河集_page31.html"
  },
  {
    "name": "西河集_page32",
    "url": "集藏/四库别集/西河集_page32.html"
  },
  {
    "name": "西河集_page33",
    "url": "集藏/四库别集/西河集_page33.html"
  },
  {
    "name": "西河集_page34",
    "url": "集藏/四库别集/西河集_page34.html"
  },
  {
    "name": "西河集_page35",
    "url": "集藏/四库别集/西河集_page35.html"
  },
  {
    "name": "西河集_page36",
    "url": "集藏/四库别集/西河集_page36.html"
  },
  {
    "name": "西河集_page37",
    "url": "集藏/四库别集/西河集_page37.html"
  },
  {
    "name": "西河集_page38",
    "url": "集藏/四库别集/西河集_page38.html"
  },
  {
    "name": "西河集_page39",
    "url": "集藏/四库别集/西河集_page39.html"
  },
  {
    "name": "西河集_page4",
    "url": "集藏/四库别集/西河集_page4.html"
  },
  {
    "name": "西河集_page40",
    "url": "集藏/四库别集/西河集_page40.html"
  },
  {
    "name": "西河集_page41",
    "url": "集藏/四库别集/西河集_page41.html"
  },
  {
    "name": "西河集_page42",
    "url": "集藏/四库别集/西河集_page42.html"
  },
  {
    "name": "西河集_page43",
    "url": "集藏/四库别集/西河集_page43.html"
  },
  {
    "name": "西河集_page44",
    "url": "集藏/四库别集/西河集_page44.html"
  },
  {
    "name": "西河集_page45",
    "url": "集藏/四库别集/西河集_page45.html"
  },
  {
    "name": "西河集_page46",
    "url": "集藏/四库别集/西河集_page46.html"
  },
  {
    "name": "西河集_page47",
    "url": "集藏/四库别集/西河集_page47.html"
  },
  {
    "name": "西河集_page48",
    "url": "集藏/四库别集/西河集_page48.html"
  },
  {
    "name": "西河集_page49",
    "url": "集藏/四库别集/西河集_page49.html"
  },
  {
    "name": "西河集_page5",
    "url": "集藏/四库别集/西河集_page5.html"
  },
  {
    "name": "西河集_page50",
    "url": "集藏/四库别集/西河集_page50.html"
  },
  {
    "name": "西河集_page51",
    "url": "集藏/四库别集/西河集_page51.html"
  },
  {
    "name": "西河集_page52",
    "url": "集藏/四库别集/西河集_page52.html"
  },
  {
    "name": "西河集_page53",
    "url": "集藏/四库别集/西河集_page53.html"
  },
  {
    "name": "西河集_page54",
    "url": "集藏/四库别集/西河集_page54.html"
  },
  {
    "name": "西河集_page55",
    "url": "集藏/四库别集/西河集_page55.html"
  },
  {
    "name": "西河集_page56",
    "url": "集藏/四库别集/西河集_page56.html"
  },
  {
    "name": "西河集_page57",
    "url": "集藏/四库别集/西河集_page57.html"
  },
  {
    "name": "西河集_page58",
    "url": "集藏/四库别集/西河集_page58.html"
  },
  {
    "name": "西河集_page59",
    "url": "集藏/四库别集/西河集_page59.html"
  },
  {
    "name": "西河集_page6",
    "url": "集藏/四库别集/西河集_page6.html"
  },
  {
    "name": "西河集_page60",
    "url": "集藏/四库别集/西河集_page60.html"
  },
  {
    "name": "西河集_page61",
    "url": "集藏/四库别集/西河集_page61.html"
  },
  {
    "name": "西河集_page62",
    "url": "集藏/四库别集/西河集_page62.html"
  },
  {
    "name": "西河集_page63",
    "url": "集藏/四库别集/西河集_page63.html"
  },
  {
    "name": "西河集_page64",
    "url": "集藏/四库别集/西河集_page64.html"
  },
  {
    "name": "西河集_page65",
    "url": "集藏/四库别集/西河集_page65.html"
  },
  {
    "name": "西河集_page66",
    "url": "集藏/四库别集/西河集_page66.html"
  },
  {
    "name": "西河集_page67",
    "url": "集藏/四库别集/西河集_page67.html"
  },
  {
    "name": "西河集_page68",
    "url": "集藏/四库别集/西河集_page68.html"
  },
  {
    "name": "西河集_page69",
    "url": "集藏/四库别集/西河集_page69.html"
  },
  {
    "name": "西河集_page7",
    "url": "集藏/四库别集/西河集_page7.html"
  },
  {
    "name": "西河集_page70",
    "url": "集藏/四库别集/西河集_page70.html"
  },
  {
    "name": "西河集_page71",
    "url": "集藏/四库别集/西河集_page71.html"
  },
  {
    "name": "西河集_page72",
    "url": "集藏/四库别集/西河集_page72.html"
  },
  {
    "name": "西河集_page73",
    "url": "集藏/四库别集/西河集_page73.html"
  },
  {
    "name": "西河集_page74",
    "url": "集藏/四库别集/西河集_page74.html"
  },
  {
    "name": "西河集_page75",
    "url": "集藏/四库别集/西河集_page75.html"
  },
  {
    "name": "西河集_page76",
    "url": "集藏/四库别集/西河集_page76.html"
  },
  {
    "name": "西河集_page77",
    "url": "集藏/四库别集/西河集_page77.html"
  },
  {
    "name": "西河集_page78",
    "url": "集藏/四库别集/西河集_page78.html"
  },
  {
    "name": "西河集_page79",
    "url": "集藏/四库别集/西河集_page79.html"
  },
  {
    "name": "西河集_page8",
    "url": "集藏/四库别集/西河集_page8.html"
  },
  {
    "name": "西河集_page80",
    "url": "集藏/四库别集/西河集_page80.html"
  },
  {
    "name": "西河集_page81",
    "url": "集藏/四库别集/西河集_page81.html"
  },
  {
    "name": "西河集_page82",
    "url": "集藏/四库别集/西河集_page82.html"
  },
  {
    "name": "西河集_page83",
    "url": "集藏/四库别集/西河集_page83.html"
  },
  {
    "name": "西河集_page84",
    "url": "集藏/四库别集/西河集_page84.html"
  },
  {
    "name": "西河集_page85",
    "url": "集藏/四库别集/西河集_page85.html"
  },
  {
    "name": "西河集_page86",
    "url": "集藏/四库别集/西河集_page86.html"
  },
  {
    "name": "西河集_page87",
    "url": "集藏/四库别集/西河集_page87.html"
  },
  {
    "name": "西河集_page88",
    "url": "集藏/四库别集/西河集_page88.html"
  },
  {
    "name": "西河集_page89",
    "url": "集藏/四库别集/西河集_page89.html"
  },
  {
    "name": "西河集_page9",
    "url": "集藏/四库别集/西河集_page9.html"
  },
  {
    "name": "西河集_page90",
    "url": "集藏/四库别集/西河集_page90.html"
  },
  {
    "name": "西河集_page91",
    "url": "集藏/四库别集/西河集_page91.html"
  },
  {
    "name": "西河集_page92",
    "url": "集藏/四库别集/西河集_page92.html"
  },
  {
    "name": "西河集_page93",
    "url": "集藏/四库别集/西河集_page93.html"
  },
  {
    "name": "西河集_page94",
    "url": "集藏/四库别集/西河集_page94.html"
  },
  {
    "name": "西河集_page95",
    "url": "集藏/四库别集/西河集_page95.html"
  },
  {
    "name": "西河集_page96",
    "url": "集藏/四库别集/西河集_page96.html"
  },
  {
    "name": "西河集_page97",
    "url": "集藏/四库别集/西河集_page97.html"
  },
  {
    "name": "西河集_page98",
    "url": "集藏/四库别集/西河集_page98.html"
  },
  {
    "name": "西河集_page99",
    "url": "集藏/四库别集/西河集_page99.html"
  },
  {
    "name": "西渡集_page1",
    "url": "集藏/四库别集/西渡集_page1.html"
  },
  {
    "name": "西渡集_page2",
    "url": "集藏/四库别集/西渡集_page2.html"
  },
  {
    "name": "西渡集_page3",
    "url": "集藏/四库别集/西渡集_page3.html"
  },
  {
    "name": "西渡集_page4",
    "url": "集藏/四库别集/西渡集_page4.html"
  },
  {
    "name": "西湖梦寻_page1",
    "url": "集藏/四库别集/西湖梦寻_page1.html"
  },
  {
    "name": "西湖梦寻_page10",
    "url": "集藏/四库别集/西湖梦寻_page10.html"
  },
  {
    "name": "西湖梦寻_page11",
    "url": "集藏/四库别集/西湖梦寻_page11.html"
  },
  {
    "name": "西湖梦寻_page12",
    "url": "集藏/四库别集/西湖梦寻_page12.html"
  },
  {
    "name": "西湖梦寻_page2",
    "url": "集藏/四库别集/西湖梦寻_page2.html"
  },
  {
    "name": "西湖梦寻_page3",
    "url": "集藏/四库别集/西湖梦寻_page3.html"
  },
  {
    "name": "西湖梦寻_page4",
    "url": "集藏/四库别集/西湖梦寻_page4.html"
  },
  {
    "name": "西湖梦寻_page5",
    "url": "集藏/四库别集/西湖梦寻_page5.html"
  },
  {
    "name": "西湖梦寻_page6",
    "url": "集藏/四库别集/西湖梦寻_page6.html"
  },
  {
    "name": "西湖梦寻_page7",
    "url": "集藏/四库别集/西湖梦寻_page7.html"
  },
  {
    "name": "西湖梦寻_page8",
    "url": "集藏/四库别集/西湖梦寻_page8.html"
  },
  {
    "name": "西湖梦寻_page9",
    "url": "集藏/四库别集/西湖梦寻_page9.html"
  },
  {
    "name": "西湖百咏_page1",
    "url": "集藏/四库别集/西湖百咏_page1.html"
  },
  {
    "name": "西湖百咏_page2",
    "url": "集藏/四库别集/西湖百咏_page2.html"
  },
  {
    "name": "西溪集_page1",
    "url": "集藏/四库别集/西溪集_page1.html"
  },
  {
    "name": "西溪集_page10",
    "url": "集藏/四库别集/西溪集_page10.html"
  },
  {
    "name": "西溪集_page11",
    "url": "集藏/四库别集/西溪集_page11.html"
  },
  {
    "name": "西溪集_page2",
    "url": "集藏/四库别集/西溪集_page2.html"
  },
  {
    "name": "西溪集_page3",
    "url": "集藏/四库别集/西溪集_page3.html"
  },
  {
    "name": "西溪集_page4",
    "url": "集藏/四库别集/西溪集_page4.html"
  },
  {
    "name": "西溪集_page5",
    "url": "集藏/四库别集/西溪集_page5.html"
  },
  {
    "name": "西溪集_page6",
    "url": "集藏/四库别集/西溪集_page6.html"
  },
  {
    "name": "西溪集_page7",
    "url": "集藏/四库别集/西溪集_page7.html"
  },
  {
    "name": "西溪集_page8",
    "url": "集藏/四库别集/西溪集_page8.html"
  },
  {
    "name": "西溪集_page9",
    "url": "集藏/四库别集/西溪集_page9.html"
  },
  {
    "name": "西郊笑端集_page1",
    "url": "集藏/四库别集/西郊笑端集_page1.html"
  },
  {
    "name": "西郊笑端集_page2",
    "url": "集藏/四库别集/西郊笑端集_page2.html"
  },
  {
    "name": "西郊笑端集_page3",
    "url": "集藏/四库别集/西郊笑端集_page3.html"
  },
  {
    "name": "西郊笑端集_page4",
    "url": "集藏/四库别集/西郊笑端集_page4.html"
  },
  {
    "name": "西郊笑端集_page5",
    "url": "集藏/四库别集/西郊笑端集_page5.html"
  },
  {
    "name": "西郊笑端集_page6",
    "url": "集藏/四库别集/西郊笑端集_page6.html"
  },
  {
    "name": "西郊笑端集_page7",
    "url": "集藏/四库别集/西郊笑端集_page7.html"
  },
  {
    "name": "西郊笑端集_page8",
    "url": "集藏/四库别集/西郊笑端集_page8.html"
  },
  {
    "name": "西郊笑端集_page9",
    "url": "集藏/四库别集/西郊笑端集_page9.html"
  },
  {
    "name": "西陂类稿_page1",
    "url": "集藏/四库别集/西陂类稿_page1.html"
  },
  {
    "name": "西陂类稿_page10",
    "url": "集藏/四库别集/西陂类稿_page10.html"
  },
  {
    "name": "西陂类稿_page11",
    "url": "集藏/四库别集/西陂类稿_page11.html"
  },
  {
    "name": "西陂类稿_page12",
    "url": "集藏/四库别集/西陂类稿_page12.html"
  },
  {
    "name": "西陂类稿_page13",
    "url": "集藏/四库别集/西陂类稿_page13.html"
  },
  {
    "name": "西陂类稿_page14",
    "url": "集藏/四库别集/西陂类稿_page14.html"
  },
  {
    "name": "西陂类稿_page15",
    "url": "集藏/四库别集/西陂类稿_page15.html"
  },
  {
    "name": "西陂类稿_page16",
    "url": "集藏/四库别集/西陂类稿_page16.html"
  },
  {
    "name": "西陂类稿_page17",
    "url": "集藏/四库别集/西陂类稿_page17.html"
  },
  {
    "name": "西陂类稿_page18",
    "url": "集藏/四库别集/西陂类稿_page18.html"
  },
  {
    "name": "西陂类稿_page19",
    "url": "集藏/四库别集/西陂类稿_page19.html"
  },
  {
    "name": "西陂类稿_page2",
    "url": "集藏/四库别集/西陂类稿_page2.html"
  },
  {
    "name": "西陂类稿_page20",
    "url": "集藏/四库别集/西陂类稿_page20.html"
  },
  {
    "name": "西陂类稿_page21",
    "url": "集藏/四库别集/西陂类稿_page21.html"
  },
  {
    "name": "西陂类稿_page22",
    "url": "集藏/四库别集/西陂类稿_page22.html"
  },
  {
    "name": "西陂类稿_page23",
    "url": "集藏/四库别集/西陂类稿_page23.html"
  },
  {
    "name": "西陂类稿_page24",
    "url": "集藏/四库别集/西陂类稿_page24.html"
  },
  {
    "name": "西陂类稿_page25",
    "url": "集藏/四库别集/西陂类稿_page25.html"
  },
  {
    "name": "西陂类稿_page26",
    "url": "集藏/四库别集/西陂类稿_page26.html"
  },
  {
    "name": "西陂类稿_page27",
    "url": "集藏/四库别集/西陂类稿_page27.html"
  },
  {
    "name": "西陂类稿_page28",
    "url": "集藏/四库别集/西陂类稿_page28.html"
  },
  {
    "name": "西陂类稿_page29",
    "url": "集藏/四库别集/西陂类稿_page29.html"
  },
  {
    "name": "西陂类稿_page3",
    "url": "集藏/四库别集/西陂类稿_page3.html"
  },
  {
    "name": "西陂类稿_page30",
    "url": "集藏/四库别集/西陂类稿_page30.html"
  },
  {
    "name": "西陂类稿_page31",
    "url": "集藏/四库别集/西陂类稿_page31.html"
  },
  {
    "name": "西陂类稿_page32",
    "url": "集藏/四库别集/西陂类稿_page32.html"
  },
  {
    "name": "西陂类稿_page33",
    "url": "集藏/四库别集/西陂类稿_page33.html"
  },
  {
    "name": "西陂类稿_page34",
    "url": "集藏/四库别集/西陂类稿_page34.html"
  },
  {
    "name": "西陂类稿_page35",
    "url": "集藏/四库别集/西陂类稿_page35.html"
  },
  {
    "name": "西陂类稿_page36",
    "url": "集藏/四库别集/西陂类稿_page36.html"
  },
  {
    "name": "西陂类稿_page37",
    "url": "集藏/四库别集/西陂类稿_page37.html"
  },
  {
    "name": "西陂类稿_page38",
    "url": "集藏/四库别集/西陂类稿_page38.html"
  },
  {
    "name": "西陂类稿_page39",
    "url": "集藏/四库别集/西陂类稿_page39.html"
  },
  {
    "name": "西陂类稿_page4",
    "url": "集藏/四库别集/西陂类稿_page4.html"
  },
  {
    "name": "西陂类稿_page40",
    "url": "集藏/四库别集/西陂类稿_page40.html"
  },
  {
    "name": "西陂类稿_page41",
    "url": "集藏/四库别集/西陂类稿_page41.html"
  },
  {
    "name": "西陂类稿_page42",
    "url": "集藏/四库别集/西陂类稿_page42.html"
  },
  {
    "name": "西陂类稿_page43",
    "url": "集藏/四库别集/西陂类稿_page43.html"
  },
  {
    "name": "西陂类稿_page44",
    "url": "集藏/四库别集/西陂类稿_page44.html"
  },
  {
    "name": "西陂类稿_page45",
    "url": "集藏/四库别集/西陂类稿_page45.html"
  },
  {
    "name": "西陂类稿_page46",
    "url": "集藏/四库别集/西陂类稿_page46.html"
  },
  {
    "name": "西陂类稿_page47",
    "url": "集藏/四库别集/西陂类稿_page47.html"
  },
  {
    "name": "西陂类稿_page48",
    "url": "集藏/四库别集/西陂类稿_page48.html"
  },
  {
    "name": "西陂类稿_page49",
    "url": "集藏/四库别集/西陂类稿_page49.html"
  },
  {
    "name": "西陂类稿_page5",
    "url": "集藏/四库别集/西陂类稿_page5.html"
  },
  {
    "name": "西陂类稿_page50",
    "url": "集藏/四库别集/西陂类稿_page50.html"
  },
  {
    "name": "西陂类稿_page51",
    "url": "集藏/四库别集/西陂类稿_page51.html"
  },
  {
    "name": "西陂类稿_page52",
    "url": "集藏/四库别集/西陂类稿_page52.html"
  },
  {
    "name": "西陂类稿_page53",
    "url": "集藏/四库别集/西陂类稿_page53.html"
  },
  {
    "name": "西陂类稿_page6",
    "url": "集藏/四库别集/西陂类稿_page6.html"
  },
  {
    "name": "西陂类稿_page7",
    "url": "集藏/四库别集/西陂类稿_page7.html"
  },
  {
    "name": "西陂类稿_page8",
    "url": "集藏/四库别集/西陂类稿_page8.html"
  },
  {
    "name": "西陂类稿_page9",
    "url": "集藏/四库别集/西陂类稿_page9.html"
  },
  {
    "name": "西隐集_page1",
    "url": "集藏/四库别集/西隐集_page1.html"
  },
  {
    "name": "西隐集_page10",
    "url": "集藏/四库别集/西隐集_page10.html"
  },
  {
    "name": "西隐集_page2",
    "url": "集藏/四库别集/西隐集_page2.html"
  },
  {
    "name": "西隐集_page3",
    "url": "集藏/四库别集/西隐集_page3.html"
  },
  {
    "name": "西隐集_page4",
    "url": "集藏/四库别集/西隐集_page4.html"
  },
  {
    "name": "西隐集_page5",
    "url": "集藏/四库别集/西隐集_page5.html"
  },
  {
    "name": "西隐集_page6",
    "url": "集藏/四库别集/西隐集_page6.html"
  },
  {
    "name": "西隐集_page7",
    "url": "集藏/四库别集/西隐集_page7.html"
  },
  {
    "name": "西隐集_page8",
    "url": "集藏/四库别集/西隐集_page8.html"
  },
  {
    "name": "西隐集_page9",
    "url": "集藏/四库别集/西隐集_page9.html"
  },
  {
    "name": "覆瓿集_page1",
    "url": "集藏/四库别集/覆瓿集_page1.html"
  },
  {
    "name": "覆瓿集_page10",
    "url": "集藏/四库别集/覆瓿集_page10.html"
  },
  {
    "name": "覆瓿集_page11",
    "url": "集藏/四库别集/覆瓿集_page11.html"
  },
  {
    "name": "覆瓿集_page12",
    "url": "集藏/四库别集/覆瓿集_page12.html"
  },
  {
    "name": "覆瓿集_page2",
    "url": "集藏/四库别集/覆瓿集_page2.html"
  },
  {
    "name": "覆瓿集_page3",
    "url": "集藏/四库别集/覆瓿集_page3.html"
  },
  {
    "name": "覆瓿集_page4",
    "url": "集藏/四库别集/覆瓿集_page4.html"
  },
  {
    "name": "覆瓿集_page5",
    "url": "集藏/四库别集/覆瓿集_page5.html"
  },
  {
    "name": "覆瓿集_page6",
    "url": "集藏/四库别集/覆瓿集_page6.html"
  },
  {
    "name": "覆瓿集_page7",
    "url": "集藏/四库别集/覆瓿集_page7.html"
  },
  {
    "name": "覆瓿集_page8",
    "url": "集藏/四库别集/覆瓿集_page8.html"
  },
  {
    "name": "覆瓿集_page9",
    "url": "集藏/四库别集/覆瓿集_page9.html"
  },
  {
    "name": "见素集_page1",
    "url": "集藏/四库别集/见素集_page1.html"
  },
  {
    "name": "见素集_page10",
    "url": "集藏/四库别集/见素集_page10.html"
  },
  {
    "name": "见素集_page11",
    "url": "集藏/四库别集/见素集_page11.html"
  },
  {
    "name": "见素集_page12",
    "url": "集藏/四库别集/见素集_page12.html"
  },
  {
    "name": "见素集_page13",
    "url": "集藏/四库别集/见素集_page13.html"
  },
  {
    "name": "见素集_page14",
    "url": "集藏/四库别集/见素集_page14.html"
  },
  {
    "name": "见素集_page15",
    "url": "集藏/四库别集/见素集_page15.html"
  },
  {
    "name": "见素集_page16",
    "url": "集藏/四库别集/见素集_page16.html"
  },
  {
    "name": "见素集_page17",
    "url": "集藏/四库别集/见素集_page17.html"
  },
  {
    "name": "见素集_page18",
    "url": "集藏/四库别集/见素集_page18.html"
  },
  {
    "name": "见素集_page19",
    "url": "集藏/四库别集/见素集_page19.html"
  },
  {
    "name": "见素集_page2",
    "url": "集藏/四库别集/见素集_page2.html"
  },
  {
    "name": "见素集_page20",
    "url": "集藏/四库别集/见素集_page20.html"
  },
  {
    "name": "见素集_page21",
    "url": "集藏/四库别集/见素集_page21.html"
  },
  {
    "name": "见素集_page22",
    "url": "集藏/四库别集/见素集_page22.html"
  },
  {
    "name": "见素集_page23",
    "url": "集藏/四库别集/见素集_page23.html"
  },
  {
    "name": "见素集_page24",
    "url": "集藏/四库别集/见素集_page24.html"
  },
  {
    "name": "见素集_page25",
    "url": "集藏/四库别集/见素集_page25.html"
  },
  {
    "name": "见素集_page26",
    "url": "集藏/四库别集/见素集_page26.html"
  },
  {
    "name": "见素集_page27",
    "url": "集藏/四库别集/见素集_page27.html"
  },
  {
    "name": "见素集_page3",
    "url": "集藏/四库别集/见素集_page3.html"
  },
  {
    "name": "见素集_page4",
    "url": "集藏/四库别集/见素集_page4.html"
  },
  {
    "name": "见素集_page5",
    "url": "集藏/四库别集/见素集_page5.html"
  },
  {
    "name": "见素集_page6",
    "url": "集藏/四库别集/见素集_page6.html"
  },
  {
    "name": "见素集_page7",
    "url": "集藏/四库别集/见素集_page7.html"
  },
  {
    "name": "见素集_page8",
    "url": "集藏/四库别集/见素集_page8.html"
  },
  {
    "name": "见素集_page9",
    "url": "集藏/四库别集/见素集_page9.html"
  },
  {
    "name": "解学士文集_page1",
    "url": "集藏/四库别集/解学士文集_page1.html"
  },
  {
    "name": "解学士文集_page10",
    "url": "集藏/四库别集/解学士文集_page10.html"
  },
  {
    "name": "解学士文集_page11",
    "url": "集藏/四库别集/解学士文集_page11.html"
  },
  {
    "name": "解学士文集_page12",
    "url": "集藏/四库别集/解学士文集_page12.html"
  },
  {
    "name": "解学士文集_page13",
    "url": "集藏/四库别集/解学士文集_page13.html"
  },
  {
    "name": "解学士文集_page14",
    "url": "集藏/四库别集/解学士文集_page14.html"
  },
  {
    "name": "解学士文集_page15",
    "url": "集藏/四库别集/解学士文集_page15.html"
  },
  {
    "name": "解学士文集_page16",
    "url": "集藏/四库别集/解学士文集_page16.html"
  },
  {
    "name": "解学士文集_page17",
    "url": "集藏/四库别集/解学士文集_page17.html"
  },
  {
    "name": "解学士文集_page18",
    "url": "集藏/四库别集/解学士文集_page18.html"
  },
  {
    "name": "解学士文集_page19",
    "url": "集藏/四库别集/解学士文集_page19.html"
  },
  {
    "name": "解学士文集_page2",
    "url": "集藏/四库别集/解学士文集_page2.html"
  },
  {
    "name": "解学士文集_page20",
    "url": "集藏/四库别集/解学士文集_page20.html"
  },
  {
    "name": "解学士文集_page21",
    "url": "集藏/四库别集/解学士文集_page21.html"
  },
  {
    "name": "解学士文集_page22",
    "url": "集藏/四库别集/解学士文集_page22.html"
  },
  {
    "name": "解学士文集_page23",
    "url": "集藏/四库别集/解学士文集_page23.html"
  },
  {
    "name": "解学士文集_page24",
    "url": "集藏/四库别集/解学士文集_page24.html"
  },
  {
    "name": "解学士文集_page25",
    "url": "集藏/四库别集/解学士文集_page25.html"
  },
  {
    "name": "解学士文集_page26",
    "url": "集藏/四库别集/解学士文集_page26.html"
  },
  {
    "name": "解学士文集_page27",
    "url": "集藏/四库别集/解学士文集_page27.html"
  },
  {
    "name": "解学士文集_page28",
    "url": "集藏/四库别集/解学士文集_page28.html"
  },
  {
    "name": "解学士文集_page29",
    "url": "集藏/四库别集/解学士文集_page29.html"
  },
  {
    "name": "解学士文集_page3",
    "url": "集藏/四库别集/解学士文集_page3.html"
  },
  {
    "name": "解学士文集_page30",
    "url": "集藏/四库别集/解学士文集_page30.html"
  },
  {
    "name": "解学士文集_page31",
    "url": "集藏/四库别集/解学士文集_page31.html"
  },
  {
    "name": "解学士文集_page32",
    "url": "集藏/四库别集/解学士文集_page32.html"
  },
  {
    "name": "解学士文集_page33",
    "url": "集藏/四库别集/解学士文集_page33.html"
  },
  {
    "name": "解学士文集_page34",
    "url": "集藏/四库别集/解学士文集_page34.html"
  },
  {
    "name": "解学士文集_page35",
    "url": "集藏/四库别集/解学士文集_page35.html"
  },
  {
    "name": "解学士文集_page36",
    "url": "集藏/四库别集/解学士文集_page36.html"
  },
  {
    "name": "解学士文集_page37",
    "url": "集藏/四库别集/解学士文集_page37.html"
  },
  {
    "name": "解学士文集_page38",
    "url": "集藏/四库别集/解学士文集_page38.html"
  },
  {
    "name": "解学士文集_page39",
    "url": "集藏/四库别集/解学士文集_page39.html"
  },
  {
    "name": "解学士文集_page4",
    "url": "集藏/四库别集/解学士文集_page4.html"
  },
  {
    "name": "解学士文集_page40",
    "url": "集藏/四库别集/解学士文集_page40.html"
  },
  {
    "name": "解学士文集_page41",
    "url": "集藏/四库别集/解学士文集_page41.html"
  },
  {
    "name": "解学士文集_page42",
    "url": "集藏/四库别集/解学士文集_page42.html"
  },
  {
    "name": "解学士文集_page43",
    "url": "集藏/四库别集/解学士文集_page43.html"
  },
  {
    "name": "解学士文集_page44",
    "url": "集藏/四库别集/解学士文集_page44.html"
  },
  {
    "name": "解学士文集_page45",
    "url": "集藏/四库别集/解学士文集_page45.html"
  },
  {
    "name": "解学士文集_page46",
    "url": "集藏/四库别集/解学士文集_page46.html"
  },
  {
    "name": "解学士文集_page47",
    "url": "集藏/四库别集/解学士文集_page47.html"
  },
  {
    "name": "解学士文集_page48",
    "url": "集藏/四库别集/解学士文集_page48.html"
  },
  {
    "name": "解学士文集_page49",
    "url": "集藏/四库别集/解学士文集_page49.html"
  },
  {
    "name": "解学士文集_page5",
    "url": "集藏/四库别集/解学士文集_page5.html"
  },
  {
    "name": "解学士文集_page50",
    "url": "集藏/四库别集/解学士文集_page50.html"
  },
  {
    "name": "解学士文集_page51",
    "url": "集藏/四库别集/解学士文集_page51.html"
  },
  {
    "name": "解学士文集_page52",
    "url": "集藏/四库别集/解学士文集_page52.html"
  },
  {
    "name": "解学士文集_page53",
    "url": "集藏/四库别集/解学士文集_page53.html"
  },
  {
    "name": "解学士文集_page54",
    "url": "集藏/四库别集/解学士文集_page54.html"
  },
  {
    "name": "解学士文集_page55",
    "url": "集藏/四库别集/解学士文集_page55.html"
  },
  {
    "name": "解学士文集_page56",
    "url": "集藏/四库别集/解学士文集_page56.html"
  },
  {
    "name": "解学士文集_page57",
    "url": "集藏/四库别集/解学士文集_page57.html"
  },
  {
    "name": "解学士文集_page58",
    "url": "集藏/四库别集/解学士文集_page58.html"
  },
  {
    "name": "解学士文集_page59",
    "url": "集藏/四库别集/解学士文集_page59.html"
  },
  {
    "name": "解学士文集_page6",
    "url": "集藏/四库别集/解学士文集_page6.html"
  },
  {
    "name": "解学士文集_page60",
    "url": "集藏/四库别集/解学士文集_page60.html"
  },
  {
    "name": "解学士文集_page61",
    "url": "集藏/四库别集/解学士文集_page61.html"
  },
  {
    "name": "解学士文集_page62",
    "url": "集藏/四库别集/解学士文集_page62.html"
  },
  {
    "name": "解学士文集_page63",
    "url": "集藏/四库别集/解学士文集_page63.html"
  },
  {
    "name": "解学士文集_page64",
    "url": "集藏/四库别集/解学士文集_page64.html"
  },
  {
    "name": "解学士文集_page65",
    "url": "集藏/四库别集/解学士文集_page65.html"
  },
  {
    "name": "解学士文集_page66",
    "url": "集藏/四库别集/解学士文集_page66.html"
  },
  {
    "name": "解学士文集_page67",
    "url": "集藏/四库别集/解学士文集_page67.html"
  },
  {
    "name": "解学士文集_page68",
    "url": "集藏/四库别集/解学士文集_page68.html"
  },
  {
    "name": "解学士文集_page7",
    "url": "集藏/四库别集/解学士文集_page7.html"
  },
  {
    "name": "解学士文集_page8",
    "url": "集藏/四库别集/解学士文集_page8.html"
  },
  {
    "name": "解学士文集_page9",
    "url": "集藏/四库别集/解学士文集_page9.html"
  },
  {
    "name": "謝叠山文集_page1",
    "url": "集藏/四库别集/謝叠山文集_page1.html"
  },
  {
    "name": "謝叠山文集_page10",
    "url": "集藏/四库别集/謝叠山文集_page10.html"
  },
  {
    "name": "謝叠山文集_page11",
    "url": "集藏/四库别集/謝叠山文集_page11.html"
  },
  {
    "name": "謝叠山文集_page12",
    "url": "集藏/四库别集/謝叠山文集_page12.html"
  },
  {
    "name": "謝叠山文集_page13",
    "url": "集藏/四库别集/謝叠山文集_page13.html"
  },
  {
    "name": "謝叠山文集_page14",
    "url": "集藏/四库别集/謝叠山文集_page14.html"
  },
  {
    "name": "謝叠山文集_page15",
    "url": "集藏/四库别集/謝叠山文集_page15.html"
  },
  {
    "name": "謝叠山文集_page16",
    "url": "集藏/四库别集/謝叠山文集_page16.html"
  },
  {
    "name": "謝叠山文集_page17",
    "url": "集藏/四库别集/謝叠山文集_page17.html"
  },
  {
    "name": "謝叠山文集_page18",
    "url": "集藏/四库别集/謝叠山文集_page18.html"
  },
  {
    "name": "謝叠山文集_page19",
    "url": "集藏/四库别集/謝叠山文集_page19.html"
  },
  {
    "name": "謝叠山文集_page2",
    "url": "集藏/四库别集/謝叠山文集_page2.html"
  },
  {
    "name": "謝叠山文集_page20",
    "url": "集藏/四库别集/謝叠山文集_page20.html"
  },
  {
    "name": "謝叠山文集_page21",
    "url": "集藏/四库别集/謝叠山文集_page21.html"
  },
  {
    "name": "謝叠山文集_page3",
    "url": "集藏/四库别集/謝叠山文集_page3.html"
  },
  {
    "name": "謝叠山文集_page4",
    "url": "集藏/四库别集/謝叠山文集_page4.html"
  },
  {
    "name": "謝叠山文集_page5",
    "url": "集藏/四库别集/謝叠山文集_page5.html"
  },
  {
    "name": "謝叠山文集_page6",
    "url": "集藏/四库别集/謝叠山文集_page6.html"
  },
  {
    "name": "謝叠山文集_page7",
    "url": "集藏/四库别集/謝叠山文集_page7.html"
  },
  {
    "name": "謝叠山文集_page8",
    "url": "集藏/四库别集/謝叠山文集_page8.html"
  },
  {
    "name": "謝叠山文集_page9",
    "url": "集藏/四库别集/謝叠山文集_page9.html"
  },
  {
    "name": "让德公祠勒石诗章_page1",
    "url": "集藏/四库别集/让德公祠勒石诗章_page1.html"
  },
  {
    "name": "让德公祠勒石诗章_page10",
    "url": "集藏/四库别集/让德公祠勒石诗章_page10.html"
  },
  {
    "name": "让德公祠勒石诗章_page11",
    "url": "集藏/四库别集/让德公祠勒石诗章_page11.html"
  },
  {
    "name": "让德公祠勒石诗章_page12",
    "url": "集藏/四库别集/让德公祠勒石诗章_page12.html"
  },
  {
    "name": "让德公祠勒石诗章_page2",
    "url": "集藏/四库别集/让德公祠勒石诗章_page2.html"
  },
  {
    "name": "让德公祠勒石诗章_page3",
    "url": "集藏/四库别集/让德公祠勒石诗章_page3.html"
  },
  {
    "name": "让德公祠勒石诗章_page4",
    "url": "集藏/四库别集/让德公祠勒石诗章_page4.html"
  },
  {
    "name": "让德公祠勒石诗章_page5",
    "url": "集藏/四库别集/让德公祠勒石诗章_page5.html"
  },
  {
    "name": "让德公祠勒石诗章_page6",
    "url": "集藏/四库别集/让德公祠勒石诗章_page6.html"
  },
  {
    "name": "让德公祠勒石诗章_page7",
    "url": "集藏/四库别集/让德公祠勒石诗章_page7.html"
  },
  {
    "name": "让德公祠勒石诗章_page8",
    "url": "集藏/四库别集/让德公祠勒石诗章_page8.html"
  },
  {
    "name": "让德公祠勒石诗章_page9",
    "url": "集藏/四库别集/让德公祠勒石诗章_page9.html"
  },
  {
    "name": "许东雷诗存_page1",
    "url": "集藏/四库别集/许东雷诗存_page1.html"
  },
  {
    "name": "许东雷诗存_page10",
    "url": "集藏/四库别集/许东雷诗存_page10.html"
  },
  {
    "name": "许东雷诗存_page11",
    "url": "集藏/四库别集/许东雷诗存_page11.html"
  },
  {
    "name": "许东雷诗存_page12",
    "url": "集藏/四库别集/许东雷诗存_page12.html"
  },
  {
    "name": "许东雷诗存_page13",
    "url": "集藏/四库别集/许东雷诗存_page13.html"
  },
  {
    "name": "许东雷诗存_page2",
    "url": "集藏/四库别集/许东雷诗存_page2.html"
  },
  {
    "name": "许东雷诗存_page3",
    "url": "集藏/四库别集/许东雷诗存_page3.html"
  },
  {
    "name": "许东雷诗存_page4",
    "url": "集藏/四库别集/许东雷诗存_page4.html"
  },
  {
    "name": "许东雷诗存_page5",
    "url": "集藏/四库别集/许东雷诗存_page5.html"
  },
  {
    "name": "许东雷诗存_page6",
    "url": "集藏/四库别集/许东雷诗存_page6.html"
  },
  {
    "name": "许东雷诗存_page7",
    "url": "集藏/四库别集/许东雷诗存_page7.html"
  },
  {
    "name": "许东雷诗存_page8",
    "url": "集藏/四库别集/许东雷诗存_page8.html"
  },
  {
    "name": "许东雷诗存_page9",
    "url": "集藏/四库别集/许东雷诗存_page9.html"
  },
  {
    "name": "许忠直集",
    "url": "集藏/四库别集/许忠直集.html"
  },
  {
    "name": "许黄门先生文集_page1",
    "url": "集藏/四库别集/许黄门先生文集_page1.html"
  },
  {
    "name": "许黄门先生文集_page10",
    "url": "集藏/四库别集/许黄门先生文集_page10.html"
  },
  {
    "name": "许黄门先生文集_page11",
    "url": "集藏/四库别集/许黄门先生文集_page11.html"
  },
  {
    "name": "许黄门先生文集_page12",
    "url": "集藏/四库别集/许黄门先生文集_page12.html"
  },
  {
    "name": "许黄门先生文集_page13",
    "url": "集藏/四库别集/许黄门先生文集_page13.html"
  },
  {
    "name": "许黄门先生文集_page14",
    "url": "集藏/四库别集/许黄门先生文集_page14.html"
  },
  {
    "name": "许黄门先生文集_page15",
    "url": "集藏/四库别集/许黄门先生文集_page15.html"
  },
  {
    "name": "许黄门先生文集_page16",
    "url": "集藏/四库别集/许黄门先生文集_page16.html"
  },
  {
    "name": "许黄门先生文集_page17",
    "url": "集藏/四库别集/许黄门先生文集_page17.html"
  },
  {
    "name": "许黄门先生文集_page18",
    "url": "集藏/四库别集/许黄门先生文集_page18.html"
  },
  {
    "name": "许黄门先生文集_page19",
    "url": "集藏/四库别集/许黄门先生文集_page19.html"
  },
  {
    "name": "许黄门先生文集_page2",
    "url": "集藏/四库别集/许黄门先生文集_page2.html"
  },
  {
    "name": "许黄门先生文集_page20",
    "url": "集藏/四库别集/许黄门先生文集_page20.html"
  },
  {
    "name": "许黄门先生文集_page21",
    "url": "集藏/四库别集/许黄门先生文集_page21.html"
  },
  {
    "name": "许黄门先生文集_page22",
    "url": "集藏/四库别集/许黄门先生文集_page22.html"
  },
  {
    "name": "许黄门先生文集_page23",
    "url": "集藏/四库别集/许黄门先生文集_page23.html"
  },
  {
    "name": "许黄门先生文集_page24",
    "url": "集藏/四库别集/许黄门先生文集_page24.html"
  },
  {
    "name": "许黄门先生文集_page25",
    "url": "集藏/四库别集/许黄门先生文集_page25.html"
  },
  {
    "name": "许黄门先生文集_page26",
    "url": "集藏/四库别集/许黄门先生文集_page26.html"
  },
  {
    "name": "许黄门先生文集_page27",
    "url": "集藏/四库别集/许黄门先生文集_page27.html"
  },
  {
    "name": "许黄门先生文集_page28",
    "url": "集藏/四库别集/许黄门先生文集_page28.html"
  },
  {
    "name": "许黄门先生文集_page29",
    "url": "集藏/四库别集/许黄门先生文集_page29.html"
  },
  {
    "name": "许黄门先生文集_page3",
    "url": "集藏/四库别集/许黄门先生文集_page3.html"
  },
  {
    "name": "许黄门先生文集_page30",
    "url": "集藏/四库别集/许黄门先生文集_page30.html"
  },
  {
    "name": "许黄门先生文集_page31",
    "url": "集藏/四库别集/许黄门先生文集_page31.html"
  },
  {
    "name": "许黄门先生文集_page32",
    "url": "集藏/四库别集/许黄门先生文集_page32.html"
  },
  {
    "name": "许黄门先生文集_page33",
    "url": "集藏/四库别集/许黄门先生文集_page33.html"
  },
  {
    "name": "许黄门先生文集_page4",
    "url": "集藏/四库别集/许黄门先生文集_page4.html"
  },
  {
    "name": "许黄门先生文集_page5",
    "url": "集藏/四库别集/许黄门先生文集_page5.html"
  },
  {
    "name": "许黄门先生文集_page6",
    "url": "集藏/四库别集/许黄门先生文集_page6.html"
  },
  {
    "name": "许黄门先生文集_page7",
    "url": "集藏/四库别集/许黄门先生文集_page7.html"
  },
  {
    "name": "许黄门先生文集_page8",
    "url": "集藏/四库别集/许黄门先生文集_page8.html"
  },
  {
    "name": "许黄门先生文集_page9",
    "url": "集藏/四库别集/许黄门先生文集_page9.html"
  },
  {
    "name": "许黄门先生诗集_page1",
    "url": "集藏/四库别集/许黄门先生诗集_page1.html"
  },
  {
    "name": "许黄门先生诗集_page10",
    "url": "集藏/四库别集/许黄门先生诗集_page10.html"
  },
  {
    "name": "许黄门先生诗集_page11",
    "url": "集藏/四库别集/许黄门先生诗集_page11.html"
  },
  {
    "name": "许黄门先生诗集_page2",
    "url": "集藏/四库别集/许黄门先生诗集_page2.html"
  },
  {
    "name": "许黄门先生诗集_page3",
    "url": "集藏/四库别集/许黄门先生诗集_page3.html"
  },
  {
    "name": "许黄门先生诗集_page4",
    "url": "集藏/四库别集/许黄门先生诗集_page4.html"
  },
  {
    "name": "许黄门先生诗集_page5",
    "url": "集藏/四库别集/许黄门先生诗集_page5.html"
  },
  {
    "name": "许黄门先生诗集_page6",
    "url": "集藏/四库别集/许黄门先生诗集_page6.html"
  },
  {
    "name": "许黄门先生诗集_page7",
    "url": "集藏/四库别集/许黄门先生诗集_page7.html"
  },
  {
    "name": "许黄门先生诗集_page8",
    "url": "集藏/四库别集/许黄门先生诗集_page8.html"
  },
  {
    "name": "许黄门先生诗集_page9",
    "url": "集藏/四库别集/许黄门先生诗集_page9.html"
  },
  {
    "name": "诚意伯文集_page1",
    "url": "集藏/四库别集/诚意伯文集_page1.html"
  },
  {
    "name": "诚意伯文集_page10",
    "url": "集藏/四库别集/诚意伯文集_page10.html"
  },
  {
    "name": "诚意伯文集_page11",
    "url": "集藏/四库别集/诚意伯文集_page11.html"
  },
  {
    "name": "诚意伯文集_page12",
    "url": "集藏/四库别集/诚意伯文集_page12.html"
  },
  {
    "name": "诚意伯文集_page13",
    "url": "集藏/四库别集/诚意伯文集_page13.html"
  },
  {
    "name": "诚意伯文集_page14",
    "url": "集藏/四库别集/诚意伯文集_page14.html"
  },
  {
    "name": "诚意伯文集_page15",
    "url": "集藏/四库别集/诚意伯文集_page15.html"
  },
  {
    "name": "诚意伯文集_page16",
    "url": "集藏/四库别集/诚意伯文集_page16.html"
  },
  {
    "name": "诚意伯文集_page17",
    "url": "集藏/四库别集/诚意伯文集_page17.html"
  },
  {
    "name": "诚意伯文集_page18",
    "url": "集藏/四库别集/诚意伯文集_page18.html"
  },
  {
    "name": "诚意伯文集_page19",
    "url": "集藏/四库别集/诚意伯文集_page19.html"
  },
  {
    "name": "诚意伯文集_page2",
    "url": "集藏/四库别集/诚意伯文集_page2.html"
  },
  {
    "name": "诚意伯文集_page20",
    "url": "集藏/四库别集/诚意伯文集_page20.html"
  },
  {
    "name": "诚意伯文集_page21",
    "url": "集藏/四库别集/诚意伯文集_page21.html"
  },
  {
    "name": "诚意伯文集_page22",
    "url": "集藏/四库别集/诚意伯文集_page22.html"
  },
  {
    "name": "诚意伯文集_page23",
    "url": "集藏/四库别集/诚意伯文集_page23.html"
  },
  {
    "name": "诚意伯文集_page24",
    "url": "集藏/四库别集/诚意伯文集_page24.html"
  },
  {
    "name": "诚意伯文集_page25",
    "url": "集藏/四库别集/诚意伯文集_page25.html"
  },
  {
    "name": "诚意伯文集_page26",
    "url": "集藏/四库别集/诚意伯文集_page26.html"
  },
  {
    "name": "诚意伯文集_page27",
    "url": "集藏/四库别集/诚意伯文集_page27.html"
  },
  {
    "name": "诚意伯文集_page28",
    "url": "集藏/四库别集/诚意伯文集_page28.html"
  },
  {
    "name": "诚意伯文集_page29",
    "url": "集藏/四库别集/诚意伯文集_page29.html"
  },
  {
    "name": "诚意伯文集_page3",
    "url": "集藏/四库别集/诚意伯文集_page3.html"
  },
  {
    "name": "诚意伯文集_page30",
    "url": "集藏/四库别集/诚意伯文集_page30.html"
  },
  {
    "name": "诚意伯文集_page31",
    "url": "集藏/四库别集/诚意伯文集_page31.html"
  },
  {
    "name": "诚意伯文集_page32",
    "url": "集藏/四库别集/诚意伯文集_page32.html"
  },
  {
    "name": "诚意伯文集_page33",
    "url": "集藏/四库别集/诚意伯文集_page33.html"
  },
  {
    "name": "诚意伯文集_page34",
    "url": "集藏/四库别集/诚意伯文集_page34.html"
  },
  {
    "name": "诚意伯文集_page35",
    "url": "集藏/四库别集/诚意伯文集_page35.html"
  },
  {
    "name": "诚意伯文集_page36",
    "url": "集藏/四库别集/诚意伯文集_page36.html"
  },
  {
    "name": "诚意伯文集_page4",
    "url": "集藏/四库别集/诚意伯文集_page4.html"
  },
  {
    "name": "诚意伯文集_page5",
    "url": "集藏/四库别集/诚意伯文集_page5.html"
  },
  {
    "name": "诚意伯文集_page6",
    "url": "集藏/四库别集/诚意伯文集_page6.html"
  },
  {
    "name": "诚意伯文集_page7",
    "url": "集藏/四库别集/诚意伯文集_page7.html"
  },
  {
    "name": "诚意伯文集_page8",
    "url": "集藏/四库别集/诚意伯文集_page8.html"
  },
  {
    "name": "诚意伯文集_page9",
    "url": "集藏/四库别集/诚意伯文集_page9.html"
  },
  {
    "name": "诚斋集_page1",
    "url": "集藏/四库别集/诚斋集_page1.html"
  },
  {
    "name": "诚斋集_page10",
    "url": "集藏/四库别集/诚斋集_page10.html"
  },
  {
    "name": "诚斋集_page100",
    "url": "集藏/四库别集/诚斋集_page100.html"
  },
  {
    "name": "诚斋集_page101",
    "url": "集藏/四库别集/诚斋集_page101.html"
  },
  {
    "name": "诚斋集_page102",
    "url": "集藏/四库别集/诚斋集_page102.html"
  },
  {
    "name": "诚斋集_page103",
    "url": "集藏/四库别集/诚斋集_page103.html"
  },
  {
    "name": "诚斋集_page104",
    "url": "集藏/四库别集/诚斋集_page104.html"
  },
  {
    "name": "诚斋集_page105",
    "url": "集藏/四库别集/诚斋集_page105.html"
  },
  {
    "name": "诚斋集_page106",
    "url": "集藏/四库别集/诚斋集_page106.html"
  },
  {
    "name": "诚斋集_page107",
    "url": "集藏/四库别集/诚斋集_page107.html"
  },
  {
    "name": "诚斋集_page108",
    "url": "集藏/四库别集/诚斋集_page108.html"
  },
  {
    "name": "诚斋集_page109",
    "url": "集藏/四库别集/诚斋集_page109.html"
  },
  {
    "name": "诚斋集_page11",
    "url": "集藏/四库别集/诚斋集_page11.html"
  },
  {
    "name": "诚斋集_page110",
    "url": "集藏/四库别集/诚斋集_page110.html"
  },
  {
    "name": "诚斋集_page111",
    "url": "集藏/四库别集/诚斋集_page111.html"
  },
  {
    "name": "诚斋集_page112",
    "url": "集藏/四库别集/诚斋集_page112.html"
  },
  {
    "name": "诚斋集_page113",
    "url": "集藏/四库别集/诚斋集_page113.html"
  },
  {
    "name": "诚斋集_page114",
    "url": "集藏/四库别集/诚斋集_page114.html"
  },
  {
    "name": "诚斋集_page115",
    "url": "集藏/四库别集/诚斋集_page115.html"
  },
  {
    "name": "诚斋集_page116",
    "url": "集藏/四库别集/诚斋集_page116.html"
  },
  {
    "name": "诚斋集_page117",
    "url": "集藏/四库别集/诚斋集_page117.html"
  },
  {
    "name": "诚斋集_page118",
    "url": "集藏/四库别集/诚斋集_page118.html"
  },
  {
    "name": "诚斋集_page119",
    "url": "集藏/四库别集/诚斋集_page119.html"
  },
  {
    "name": "诚斋集_page12",
    "url": "集藏/四库别集/诚斋集_page12.html"
  },
  {
    "name": "诚斋集_page120",
    "url": "集藏/四库别集/诚斋集_page120.html"
  },
  {
    "name": "诚斋集_page13",
    "url": "集藏/四库别集/诚斋集_page13.html"
  },
  {
    "name": "诚斋集_page14",
    "url": "集藏/四库别集/诚斋集_page14.html"
  },
  {
    "name": "诚斋集_page15",
    "url": "集藏/四库别集/诚斋集_page15.html"
  },
  {
    "name": "诚斋集_page16",
    "url": "集藏/四库别集/诚斋集_page16.html"
  },
  {
    "name": "诚斋集_page17",
    "url": "集藏/四库别集/诚斋集_page17.html"
  },
  {
    "name": "诚斋集_page18",
    "url": "集藏/四库别集/诚斋集_page18.html"
  },
  {
    "name": "诚斋集_page19",
    "url": "集藏/四库别集/诚斋集_page19.html"
  },
  {
    "name": "诚斋集_page2",
    "url": "集藏/四库别集/诚斋集_page2.html"
  },
  {
    "name": "诚斋集_page20",
    "url": "集藏/四库别集/诚斋集_page20.html"
  },
  {
    "name": "诚斋集_page21",
    "url": "集藏/四库别集/诚斋集_page21.html"
  },
  {
    "name": "诚斋集_page22",
    "url": "集藏/四库别集/诚斋集_page22.html"
  },
  {
    "name": "诚斋集_page23",
    "url": "集藏/四库别集/诚斋集_page23.html"
  },
  {
    "name": "诚斋集_page24",
    "url": "集藏/四库别集/诚斋集_page24.html"
  },
  {
    "name": "诚斋集_page25",
    "url": "集藏/四库别集/诚斋集_page25.html"
  },
  {
    "name": "诚斋集_page26",
    "url": "集藏/四库别集/诚斋集_page26.html"
  },
  {
    "name": "诚斋集_page27",
    "url": "集藏/四库别集/诚斋集_page27.html"
  },
  {
    "name": "诚斋集_page28",
    "url": "集藏/四库别集/诚斋集_page28.html"
  },
  {
    "name": "诚斋集_page29",
    "url": "集藏/四库别集/诚斋集_page29.html"
  },
  {
    "name": "诚斋集_page3",
    "url": "集藏/四库别集/诚斋集_page3.html"
  },
  {
    "name": "诚斋集_page30",
    "url": "集藏/四库别集/诚斋集_page30.html"
  },
  {
    "name": "诚斋集_page31",
    "url": "集藏/四库别集/诚斋集_page31.html"
  },
  {
    "name": "诚斋集_page32",
    "url": "集藏/四库别集/诚斋集_page32.html"
  },
  {
    "name": "诚斋集_page33",
    "url": "集藏/四库别集/诚斋集_page33.html"
  },
  {
    "name": "诚斋集_page34",
    "url": "集藏/四库别集/诚斋集_page34.html"
  },
  {
    "name": "诚斋集_page35",
    "url": "集藏/四库别集/诚斋集_page35.html"
  },
  {
    "name": "诚斋集_page36",
    "url": "集藏/四库别集/诚斋集_page36.html"
  },
  {
    "name": "诚斋集_page37",
    "url": "集藏/四库别集/诚斋集_page37.html"
  },
  {
    "name": "诚斋集_page38",
    "url": "集藏/四库别集/诚斋集_page38.html"
  },
  {
    "name": "诚斋集_page39",
    "url": "集藏/四库别集/诚斋集_page39.html"
  },
  {
    "name": "诚斋集_page4",
    "url": "集藏/四库别集/诚斋集_page4.html"
  },
  {
    "name": "诚斋集_page40",
    "url": "集藏/四库别集/诚斋集_page40.html"
  },
  {
    "name": "诚斋集_page41",
    "url": "集藏/四库别集/诚斋集_page41.html"
  },
  {
    "name": "诚斋集_page42",
    "url": "集藏/四库别集/诚斋集_page42.html"
  },
  {
    "name": "诚斋集_page43",
    "url": "集藏/四库别集/诚斋集_page43.html"
  },
  {
    "name": "诚斋集_page44",
    "url": "集藏/四库别集/诚斋集_page44.html"
  },
  {
    "name": "诚斋集_page45",
    "url": "集藏/四库别集/诚斋集_page45.html"
  },
  {
    "name": "诚斋集_page46",
    "url": "集藏/四库别集/诚斋集_page46.html"
  },
  {
    "name": "诚斋集_page47",
    "url": "集藏/四库别集/诚斋集_page47.html"
  },
  {
    "name": "诚斋集_page48",
    "url": "集藏/四库别集/诚斋集_page48.html"
  },
  {
    "name": "诚斋集_page49",
    "url": "集藏/四库别集/诚斋集_page49.html"
  },
  {
    "name": "诚斋集_page5",
    "url": "集藏/四库别集/诚斋集_page5.html"
  },
  {
    "name": "诚斋集_page50",
    "url": "集藏/四库别集/诚斋集_page50.html"
  },
  {
    "name": "诚斋集_page51",
    "url": "集藏/四库别集/诚斋集_page51.html"
  },
  {
    "name": "诚斋集_page52",
    "url": "集藏/四库别集/诚斋集_page52.html"
  },
  {
    "name": "诚斋集_page53",
    "url": "集藏/四库别集/诚斋集_page53.html"
  },
  {
    "name": "诚斋集_page54",
    "url": "集藏/四库别集/诚斋集_page54.html"
  },
  {
    "name": "诚斋集_page55",
    "url": "集藏/四库别集/诚斋集_page55.html"
  },
  {
    "name": "诚斋集_page56",
    "url": "集藏/四库别集/诚斋集_page56.html"
  },
  {
    "name": "诚斋集_page57",
    "url": "集藏/四库别集/诚斋集_page57.html"
  },
  {
    "name": "诚斋集_page58",
    "url": "集藏/四库别集/诚斋集_page58.html"
  },
  {
    "name": "诚斋集_page59",
    "url": "集藏/四库别集/诚斋集_page59.html"
  },
  {
    "name": "诚斋集_page6",
    "url": "集藏/四库别集/诚斋集_page6.html"
  },
  {
    "name": "诚斋集_page60",
    "url": "集藏/四库别集/诚斋集_page60.html"
  },
  {
    "name": "诚斋集_page61",
    "url": "集藏/四库别集/诚斋集_page61.html"
  },
  {
    "name": "诚斋集_page62",
    "url": "集藏/四库别集/诚斋集_page62.html"
  },
  {
    "name": "诚斋集_page63",
    "url": "集藏/四库别集/诚斋集_page63.html"
  },
  {
    "name": "诚斋集_page64",
    "url": "集藏/四库别集/诚斋集_page64.html"
  },
  {
    "name": "诚斋集_page65",
    "url": "集藏/四库别集/诚斋集_page65.html"
  },
  {
    "name": "诚斋集_page66",
    "url": "集藏/四库别集/诚斋集_page66.html"
  },
  {
    "name": "诚斋集_page67",
    "url": "集藏/四库别集/诚斋集_page67.html"
  },
  {
    "name": "诚斋集_page68",
    "url": "集藏/四库别集/诚斋集_page68.html"
  },
  {
    "name": "诚斋集_page69",
    "url": "集藏/四库别集/诚斋集_page69.html"
  },
  {
    "name": "诚斋集_page7",
    "url": "集藏/四库别集/诚斋集_page7.html"
  },
  {
    "name": "诚斋集_page70",
    "url": "集藏/四库别集/诚斋集_page70.html"
  },
  {
    "name": "诚斋集_page71",
    "url": "集藏/四库别集/诚斋集_page71.html"
  },
  {
    "name": "诚斋集_page72",
    "url": "集藏/四库别集/诚斋集_page72.html"
  },
  {
    "name": "诚斋集_page73",
    "url": "集藏/四库别集/诚斋集_page73.html"
  },
  {
    "name": "诚斋集_page74",
    "url": "集藏/四库别集/诚斋集_page74.html"
  },
  {
    "name": "诚斋集_page75",
    "url": "集藏/四库别集/诚斋集_page75.html"
  },
  {
    "name": "诚斋集_page76",
    "url": "集藏/四库别集/诚斋集_page76.html"
  },
  {
    "name": "诚斋集_page77",
    "url": "集藏/四库别集/诚斋集_page77.html"
  },
  {
    "name": "诚斋集_page78",
    "url": "集藏/四库别集/诚斋集_page78.html"
  },
  {
    "name": "诚斋集_page79",
    "url": "集藏/四库别集/诚斋集_page79.html"
  },
  {
    "name": "诚斋集_page8",
    "url": "集藏/四库别集/诚斋集_page8.html"
  },
  {
    "name": "诚斋集_page80",
    "url": "集藏/四库别集/诚斋集_page80.html"
  },
  {
    "name": "诚斋集_page81",
    "url": "集藏/四库别集/诚斋集_page81.html"
  },
  {
    "name": "诚斋集_page82",
    "url": "集藏/四库别集/诚斋集_page82.html"
  },
  {
    "name": "诚斋集_page83",
    "url": "集藏/四库别集/诚斋集_page83.html"
  },
  {
    "name": "诚斋集_page84",
    "url": "集藏/四库别集/诚斋集_page84.html"
  },
  {
    "name": "诚斋集_page85",
    "url": "集藏/四库别集/诚斋集_page85.html"
  },
  {
    "name": "诚斋集_page86",
    "url": "集藏/四库别集/诚斋集_page86.html"
  },
  {
    "name": "诚斋集_page87",
    "url": "集藏/四库别集/诚斋集_page87.html"
  },
  {
    "name": "诚斋集_page88",
    "url": "集藏/四库别集/诚斋集_page88.html"
  },
  {
    "name": "诚斋集_page89",
    "url": "集藏/四库别集/诚斋集_page89.html"
  },
  {
    "name": "诚斋集_page9",
    "url": "集藏/四库别集/诚斋集_page9.html"
  },
  {
    "name": "诚斋集_page90",
    "url": "集藏/四库别集/诚斋集_page90.html"
  },
  {
    "name": "诚斋集_page91",
    "url": "集藏/四库别集/诚斋集_page91.html"
  },
  {
    "name": "诚斋集_page92",
    "url": "集藏/四库别集/诚斋集_page92.html"
  },
  {
    "name": "诚斋集_page93",
    "url": "集藏/四库别集/诚斋集_page93.html"
  },
  {
    "name": "诚斋集_page94",
    "url": "集藏/四库别集/诚斋集_page94.html"
  },
  {
    "name": "诚斋集_page95",
    "url": "集藏/四库别集/诚斋集_page95.html"
  },
  {
    "name": "诚斋集_page96",
    "url": "集藏/四库别集/诚斋集_page96.html"
  },
  {
    "name": "诚斋集_page97",
    "url": "集藏/四库别集/诚斋集_page97.html"
  },
  {
    "name": "诚斋集_page98",
    "url": "集藏/四库别集/诚斋集_page98.html"
  },
  {
    "name": "诚斋集_page99",
    "url": "集藏/四库别集/诚斋集_page99.html"
  },
  {
    "name": "说剑吟",
    "url": "集藏/四库别集/说剑吟.html"
  },
  {
    "name": "说学斋稿_page1",
    "url": "集藏/四库别集/说学斋稿_page1.html"
  },
  {
    "name": "说学斋稿_page2",
    "url": "集藏/四库别集/说学斋稿_page2.html"
  },
  {
    "name": "说学斋稿_page3",
    "url": "集藏/四库别集/说学斋稿_page3.html"
  },
  {
    "name": "说学斋稿_page4",
    "url": "集藏/四库别集/说学斋稿_page4.html"
  },
  {
    "name": "说学斋稿_page5",
    "url": "集藏/四库别集/说学斋稿_page5.html"
  },
  {
    "name": "说学斋稿_page6",
    "url": "集藏/四库别集/说学斋稿_page6.html"
  },
  {
    "name": "说学斋稿_page7",
    "url": "集藏/四库别集/说学斋稿_page7.html"
  },
  {
    "name": "读书后_page1",
    "url": "集藏/四库别集/读书后_page1.html"
  },
  {
    "name": "读书后_page2",
    "url": "集藏/四库别集/读书后_page2.html"
  },
  {
    "name": "读书后_page3",
    "url": "集藏/四库别集/读书后_page3.html"
  },
  {
    "name": "读书后_page4",
    "url": "集藏/四库别集/读书后_page4.html"
  },
  {
    "name": "读书后_page5",
    "url": "集藏/四库别集/读书后_page5.html"
  },
  {
    "name": "读书后_page6",
    "url": "集藏/四库别集/读书后_page6.html"
  },
  {
    "name": "读书后_page7",
    "url": "集藏/四库别集/读书后_page7.html"
  },
  {
    "name": "读书后_page8",
    "url": "集藏/四库别集/读书后_page8.html"
  },
  {
    "name": "读书后_page9",
    "url": "集藏/四库别集/读书后_page9.html"
  },
  {
    "name": "读书斋偶存稿_page1",
    "url": "集藏/四库别集/读书斋偶存稿_page1.html"
  },
  {
    "name": "读书斋偶存稿_page10",
    "url": "集藏/四库别集/读书斋偶存稿_page10.html"
  },
  {
    "name": "读书斋偶存稿_page11",
    "url": "集藏/四库别集/读书斋偶存稿_page11.html"
  },
  {
    "name": "读书斋偶存稿_page12",
    "url": "集藏/四库别集/读书斋偶存稿_page12.html"
  },
  {
    "name": "读书斋偶存稿_page13",
    "url": "集藏/四库别集/读书斋偶存稿_page13.html"
  },
  {
    "name": "读书斋偶存稿_page2",
    "url": "集藏/四库别集/读书斋偶存稿_page2.html"
  },
  {
    "name": "读书斋偶存稿_page3",
    "url": "集藏/四库别集/读书斋偶存稿_page3.html"
  },
  {
    "name": "读书斋偶存稿_page4",
    "url": "集藏/四库别集/读书斋偶存稿_page4.html"
  },
  {
    "name": "读书斋偶存稿_page5",
    "url": "集藏/四库别集/读书斋偶存稿_page5.html"
  },
  {
    "name": "读书斋偶存稿_page6",
    "url": "集藏/四库别集/读书斋偶存稿_page6.html"
  },
  {
    "name": "读书斋偶存稿_page7",
    "url": "集藏/四库别集/读书斋偶存稿_page7.html"
  },
  {
    "name": "读书斋偶存稿_page8",
    "url": "集藏/四库别集/读书斋偶存稿_page8.html"
  },
  {
    "name": "读书斋偶存稿_page9",
    "url": "集藏/四库别集/读书斋偶存稿_page9.html"
  },
  {
    "name": "谢宣城集_page1",
    "url": "集藏/四库别集/谢宣城集_page1.html"
  },
  {
    "name": "谢宣城集_page2",
    "url": "集藏/四库别集/谢宣城集_page2.html"
  },
  {
    "name": "谢宣城集_page3",
    "url": "集藏/四库别集/谢宣城集_page3.html"
  },
  {
    "name": "谢宣城集_page4",
    "url": "集藏/四库别集/谢宣城集_page4.html"
  },
  {
    "name": "谢宣城集_page5",
    "url": "集藏/四库别集/谢宣城集_page5.html"
  },
  {
    "name": "谢宣城集_page6",
    "url": "集藏/四库别集/谢宣城集_page6.html"
  },
  {
    "name": "谢文庄公集_page1",
    "url": "集藏/四库别集/谢文庄公集_page1.html"
  },
  {
    "name": "谢文庄公集_page2",
    "url": "集藏/四库别集/谢文庄公集_page2.html"
  },
  {
    "name": "谢文庄公集_page3",
    "url": "集藏/四库别集/谢文庄公集_page3.html"
  },
  {
    "name": "谢文庄公集_page4",
    "url": "集藏/四库别集/谢文庄公集_page4.html"
  },
  {
    "name": "谢文庄公集_page5",
    "url": "集藏/四库别集/谢文庄公集_page5.html"
  },
  {
    "name": "谢文庄公集_page6",
    "url": "集藏/四库别集/谢文庄公集_page6.html"
  },
  {
    "name": "谢文庄公集_page7",
    "url": "集藏/四库别集/谢文庄公集_page7.html"
  },
  {
    "name": "谦斋文录_page1",
    "url": "集藏/四库别集/谦斋文录_page1.html"
  },
  {
    "name": "谦斋文录_page10",
    "url": "集藏/四库别集/谦斋文录_page10.html"
  },
  {
    "name": "谦斋文录_page11",
    "url": "集藏/四库别集/谦斋文录_page11.html"
  },
  {
    "name": "谦斋文录_page12",
    "url": "集藏/四库别集/谦斋文录_page12.html"
  },
  {
    "name": "谦斋文录_page13",
    "url": "集藏/四库别集/谦斋文录_page13.html"
  },
  {
    "name": "谦斋文录_page14",
    "url": "集藏/四库别集/谦斋文录_page14.html"
  },
  {
    "name": "谦斋文录_page2",
    "url": "集藏/四库别集/谦斋文录_page2.html"
  },
  {
    "name": "谦斋文录_page3",
    "url": "集藏/四库别集/谦斋文录_page3.html"
  },
  {
    "name": "谦斋文录_page4",
    "url": "集藏/四库别集/谦斋文录_page4.html"
  },
  {
    "name": "谦斋文录_page5",
    "url": "集藏/四库别集/谦斋文录_page5.html"
  },
  {
    "name": "谦斋文录_page6",
    "url": "集藏/四库别集/谦斋文录_page6.html"
  },
  {
    "name": "谦斋文录_page7",
    "url": "集藏/四库别集/谦斋文录_page7.html"
  },
  {
    "name": "谦斋文录_page8",
    "url": "集藏/四库别集/谦斋文录_page8.html"
  },
  {
    "name": "谦斋文录_page9",
    "url": "集藏/四库别集/谦斋文录_page9.html"
  },
  {
    "name": "谷响集_page1",
    "url": "集藏/四库别集/谷响集_page1.html"
  },
  {
    "name": "谷响集_page10",
    "url": "集藏/四库别集/谷响集_page10.html"
  },
  {
    "name": "谷响集_page11",
    "url": "集藏/四库别集/谷响集_page11.html"
  },
  {
    "name": "谷响集_page12",
    "url": "集藏/四库别集/谷响集_page12.html"
  },
  {
    "name": "谷响集_page13",
    "url": "集藏/四库别集/谷响集_page13.html"
  },
  {
    "name": "谷响集_page14",
    "url": "集藏/四库别集/谷响集_page14.html"
  },
  {
    "name": "谷响集_page15",
    "url": "集藏/四库别集/谷响集_page15.html"
  },
  {
    "name": "谷响集_page2",
    "url": "集藏/四库别集/谷响集_page2.html"
  },
  {
    "name": "谷响集_page3",
    "url": "集藏/四库别集/谷响集_page3.html"
  },
  {
    "name": "谷响集_page4",
    "url": "集藏/四库别集/谷响集_page4.html"
  },
  {
    "name": "谷响集_page5",
    "url": "集藏/四库别集/谷响集_page5.html"
  },
  {
    "name": "谷响集_page6",
    "url": "集藏/四库别集/谷响集_page6.html"
  },
  {
    "name": "谷响集_page7",
    "url": "集藏/四库别集/谷响集_page7.html"
  },
  {
    "name": "谷响集_page8",
    "url": "集藏/四库别集/谷响集_page8.html"
  },
  {
    "name": "谷响集_page9",
    "url": "集藏/四库别集/谷响集_page9.html"
  },
  {
    "name": "谷城山馆诗_page1",
    "url": "集藏/四库别集/谷城山馆诗_page1.html"
  },
  {
    "name": "谷城山馆诗_page10",
    "url": "集藏/四库别集/谷城山馆诗_page10.html"
  },
  {
    "name": "谷城山馆诗_page11",
    "url": "集藏/四库别集/谷城山馆诗_page11.html"
  },
  {
    "name": "谷城山馆诗_page12",
    "url": "集藏/四库别集/谷城山馆诗_page12.html"
  },
  {
    "name": "谷城山馆诗_page13",
    "url": "集藏/四库别集/谷城山馆诗_page13.html"
  },
  {
    "name": "谷城山馆诗_page14",
    "url": "集藏/四库别集/谷城山馆诗_page14.html"
  },
  {
    "name": "谷城山馆诗_page15",
    "url": "集藏/四库别集/谷城山馆诗_page15.html"
  },
  {
    "name": "谷城山馆诗_page16",
    "url": "集藏/四库别集/谷城山馆诗_page16.html"
  },
  {
    "name": "谷城山馆诗_page17",
    "url": "集藏/四库别集/谷城山馆诗_page17.html"
  },
  {
    "name": "谷城山馆诗_page18",
    "url": "集藏/四库别集/谷城山馆诗_page18.html"
  },
  {
    "name": "谷城山馆诗_page19",
    "url": "集藏/四库别集/谷城山馆诗_page19.html"
  },
  {
    "name": "谷城山馆诗_page2",
    "url": "集藏/四库别集/谷城山馆诗_page2.html"
  },
  {
    "name": "谷城山馆诗_page20",
    "url": "集藏/四库别集/谷城山馆诗_page20.html"
  },
  {
    "name": "谷城山馆诗_page21",
    "url": "集藏/四库别集/谷城山馆诗_page21.html"
  },
  {
    "name": "谷城山馆诗_page22",
    "url": "集藏/四库别集/谷城山馆诗_page22.html"
  },
  {
    "name": "谷城山馆诗_page23",
    "url": "集藏/四库别集/谷城山馆诗_page23.html"
  },
  {
    "name": "谷城山馆诗_page24",
    "url": "集藏/四库别集/谷城山馆诗_page24.html"
  },
  {
    "name": "谷城山馆诗_page25",
    "url": "集藏/四库别集/谷城山馆诗_page25.html"
  },
  {
    "name": "谷城山馆诗_page26",
    "url": "集藏/四库别集/谷城山馆诗_page26.html"
  },
  {
    "name": "谷城山馆诗_page27",
    "url": "集藏/四库别集/谷城山馆诗_page27.html"
  },
  {
    "name": "谷城山馆诗_page28",
    "url": "集藏/四库别集/谷城山馆诗_page28.html"
  },
  {
    "name": "谷城山馆诗_page29",
    "url": "集藏/四库别集/谷城山馆诗_page29.html"
  },
  {
    "name": "谷城山馆诗_page3",
    "url": "集藏/四库别集/谷城山馆诗_page3.html"
  },
  {
    "name": "谷城山馆诗_page30",
    "url": "集藏/四库别集/谷城山馆诗_page30.html"
  },
  {
    "name": "谷城山馆诗_page31",
    "url": "集藏/四库别集/谷城山馆诗_page31.html"
  },
  {
    "name": "谷城山馆诗_page32",
    "url": "集藏/四库别集/谷城山馆诗_page32.html"
  },
  {
    "name": "谷城山馆诗_page33",
    "url": "集藏/四库别集/谷城山馆诗_page33.html"
  },
  {
    "name": "谷城山馆诗_page34",
    "url": "集藏/四库别集/谷城山馆诗_page34.html"
  },
  {
    "name": "谷城山馆诗_page35",
    "url": "集藏/四库别集/谷城山馆诗_page35.html"
  },
  {
    "name": "谷城山馆诗_page36",
    "url": "集藏/四库别集/谷城山馆诗_page36.html"
  },
  {
    "name": "谷城山馆诗_page37",
    "url": "集藏/四库别集/谷城山馆诗_page37.html"
  },
  {
    "name": "谷城山馆诗_page38",
    "url": "集藏/四库别集/谷城山馆诗_page38.html"
  },
  {
    "name": "谷城山馆诗_page39",
    "url": "集藏/四库别集/谷城山馆诗_page39.html"
  },
  {
    "name": "谷城山馆诗_page4",
    "url": "集藏/四库别集/谷城山馆诗_page4.html"
  },
  {
    "name": "谷城山馆诗_page40",
    "url": "集藏/四库别集/谷城山馆诗_page40.html"
  },
  {
    "name": "谷城山馆诗_page41",
    "url": "集藏/四库别集/谷城山馆诗_page41.html"
  },
  {
    "name": "谷城山馆诗_page42",
    "url": "集藏/四库别集/谷城山馆诗_page42.html"
  },
  {
    "name": "谷城山馆诗_page43",
    "url": "集藏/四库别集/谷城山馆诗_page43.html"
  },
  {
    "name": "谷城山馆诗_page44",
    "url": "集藏/四库别集/谷城山馆诗_page44.html"
  },
  {
    "name": "谷城山馆诗_page45",
    "url": "集藏/四库别集/谷城山馆诗_page45.html"
  },
  {
    "name": "谷城山馆诗_page46",
    "url": "集藏/四库别集/谷城山馆诗_page46.html"
  },
  {
    "name": "谷城山馆诗_page5",
    "url": "集藏/四库别集/谷城山馆诗_page5.html"
  },
  {
    "name": "谷城山馆诗_page6",
    "url": "集藏/四库别集/谷城山馆诗_page6.html"
  },
  {
    "name": "谷城山馆诗_page7",
    "url": "集藏/四库别集/谷城山馆诗_page7.html"
  },
  {
    "name": "谷城山馆诗_page8",
    "url": "集藏/四库别集/谷城山馆诗_page8.html"
  },
  {
    "name": "谷城山馆诗_page9",
    "url": "集藏/四库别集/谷城山馆诗_page9.html"
  },
  {
    "name": "谷城山馆诗集_page1",
    "url": "集藏/四库别集/谷城山馆诗集_page1.html"
  },
  {
    "name": "谷城山馆诗集_page10",
    "url": "集藏/四库别集/谷城山馆诗集_page10.html"
  },
  {
    "name": "谷城山馆诗集_page11",
    "url": "集藏/四库别集/谷城山馆诗集_page11.html"
  },
  {
    "name": "谷城山馆诗集_page12",
    "url": "集藏/四库别集/谷城山馆诗集_page12.html"
  },
  {
    "name": "谷城山馆诗集_page13",
    "url": "集藏/四库别集/谷城山馆诗集_page13.html"
  },
  {
    "name": "谷城山馆诗集_page14",
    "url": "集藏/四库别集/谷城山馆诗集_page14.html"
  },
  {
    "name": "谷城山馆诗集_page15",
    "url": "集藏/四库别集/谷城山馆诗集_page15.html"
  },
  {
    "name": "谷城山馆诗集_page16",
    "url": "集藏/四库别集/谷城山馆诗集_page16.html"
  },
  {
    "name": "谷城山馆诗集_page17",
    "url": "集藏/四库别集/谷城山馆诗集_page17.html"
  },
  {
    "name": "谷城山馆诗集_page18",
    "url": "集藏/四库别集/谷城山馆诗集_page18.html"
  },
  {
    "name": "谷城山馆诗集_page19",
    "url": "集藏/四库别集/谷城山馆诗集_page19.html"
  },
  {
    "name": "谷城山馆诗集_page2",
    "url": "集藏/四库别集/谷城山馆诗集_page2.html"
  },
  {
    "name": "谷城山馆诗集_page20",
    "url": "集藏/四库别集/谷城山馆诗集_page20.html"
  },
  {
    "name": "谷城山馆诗集_page21",
    "url": "集藏/四库别集/谷城山馆诗集_page21.html"
  },
  {
    "name": "谷城山馆诗集_page22",
    "url": "集藏/四库别集/谷城山馆诗集_page22.html"
  },
  {
    "name": "谷城山馆诗集_page23",
    "url": "集藏/四库别集/谷城山馆诗集_page23.html"
  },
  {
    "name": "谷城山馆诗集_page24",
    "url": "集藏/四库别集/谷城山馆诗集_page24.html"
  },
  {
    "name": "谷城山馆诗集_page25",
    "url": "集藏/四库别集/谷城山馆诗集_page25.html"
  },
  {
    "name": "谷城山馆诗集_page3",
    "url": "集藏/四库别集/谷城山馆诗集_page3.html"
  },
  {
    "name": "谷城山馆诗集_page4",
    "url": "集藏/四库别集/谷城山馆诗集_page4.html"
  },
  {
    "name": "谷城山馆诗集_page5",
    "url": "集藏/四库别集/谷城山馆诗集_page5.html"
  },
  {
    "name": "谷城山馆诗集_page6",
    "url": "集藏/四库别集/谷城山馆诗集_page6.html"
  },
  {
    "name": "谷城山馆诗集_page7",
    "url": "集藏/四库别集/谷城山馆诗集_page7.html"
  },
  {
    "name": "谷城山馆诗集_page8",
    "url": "集藏/四库别集/谷城山馆诗集_page8.html"
  },
  {
    "name": "谷城山馆诗集_page9",
    "url": "集藏/四库别集/谷城山馆诗集_page9.html"
  },
  {
    "name": "象山集象山语录_page1",
    "url": "集藏/四库别集/象山集象山语录_page1.html"
  },
  {
    "name": "象山集象山语录_page10",
    "url": "集藏/四库别集/象山集象山语录_page10.html"
  },
  {
    "name": "象山集象山语录_page11",
    "url": "集藏/四库别集/象山集象山语录_page11.html"
  },
  {
    "name": "象山集象山语录_page12",
    "url": "集藏/四库别集/象山集象山语录_page12.html"
  },
  {
    "name": "象山集象山语录_page13",
    "url": "集藏/四库别集/象山集象山语录_page13.html"
  },
  {
    "name": "象山集象山语录_page14",
    "url": "集藏/四库别集/象山集象山语录_page14.html"
  },
  {
    "name": "象山集象山语录_page15",
    "url": "集藏/四库别集/象山集象山语录_page15.html"
  },
  {
    "name": "象山集象山语录_page16",
    "url": "集藏/四库别集/象山集象山语录_page16.html"
  },
  {
    "name": "象山集象山语录_page17",
    "url": "集藏/四库别集/象山集象山语录_page17.html"
  },
  {
    "name": "象山集象山语录_page18",
    "url": "集藏/四库别集/象山集象山语录_page18.html"
  },
  {
    "name": "象山集象山语录_page19",
    "url": "集藏/四库别集/象山集象山语录_page19.html"
  },
  {
    "name": "象山集象山语录_page2",
    "url": "集藏/四库别集/象山集象山语录_page2.html"
  },
  {
    "name": "象山集象山语录_page20",
    "url": "集藏/四库别集/象山集象山语录_page20.html"
  },
  {
    "name": "象山集象山语录_page21",
    "url": "集藏/四库别集/象山集象山语录_page21.html"
  },
  {
    "name": "象山集象山语录_page22",
    "url": "集藏/四库别集/象山集象山语录_page22.html"
  },
  {
    "name": "象山集象山语录_page23",
    "url": "集藏/四库别集/象山集象山语录_page23.html"
  },
  {
    "name": "象山集象山语录_page3",
    "url": "集藏/四库别集/象山集象山语录_page3.html"
  },
  {
    "name": "象山集象山语录_page4",
    "url": "集藏/四库别集/象山集象山语录_page4.html"
  },
  {
    "name": "象山集象山语录_page5",
    "url": "集藏/四库别集/象山集象山语录_page5.html"
  },
  {
    "name": "象山集象山语录_page6",
    "url": "集藏/四库别集/象山集象山语录_page6.html"
  },
  {
    "name": "象山集象山语录_page7",
    "url": "集藏/四库别集/象山集象山语录_page7.html"
  },
  {
    "name": "象山集象山语录_page8",
    "url": "集藏/四库别集/象山集象山语录_page8.html"
  },
  {
    "name": "象山集象山语录_page9",
    "url": "集藏/四库别集/象山集象山语录_page9.html"
  },
  {
    "name": "豫章文集_page1",
    "url": "集藏/四库别集/豫章文集_page1.html"
  },
  {
    "name": "豫章文集_page10",
    "url": "集藏/四库别集/豫章文集_page10.html"
  },
  {
    "name": "豫章文集_page11",
    "url": "集藏/四库别集/豫章文集_page11.html"
  },
  {
    "name": "豫章文集_page2",
    "url": "集藏/四库别集/豫章文集_page2.html"
  },
  {
    "name": "豫章文集_page3",
    "url": "集藏/四库别集/豫章文集_page3.html"
  },
  {
    "name": "豫章文集_page4",
    "url": "集藏/四库别集/豫章文集_page4.html"
  },
  {
    "name": "豫章文集_page5",
    "url": "集藏/四库别集/豫章文集_page5.html"
  },
  {
    "name": "豫章文集_page6",
    "url": "集藏/四库别集/豫章文集_page6.html"
  },
  {
    "name": "豫章文集_page7",
    "url": "集藏/四库别集/豫章文集_page7.html"
  },
  {
    "name": "豫章文集_page8",
    "url": "集藏/四库别集/豫章文集_page8.html"
  },
  {
    "name": "豫章文集_page9",
    "url": "集藏/四库别集/豫章文集_page9.html"
  },
  {
    "name": "贞一斋稿_page1",
    "url": "集藏/四库别集/贞一斋稿_page1.html"
  },
  {
    "name": "贞一斋稿_page2",
    "url": "集藏/四库别集/贞一斋稿_page2.html"
  },
  {
    "name": "贞一斋稿_page3",
    "url": "集藏/四库别集/贞一斋稿_page3.html"
  },
  {
    "name": "贞一斋稿_page4",
    "url": "集藏/四库别集/贞一斋稿_page4.html"
  },
  {
    "name": "贞一斋稿_page5",
    "url": "集藏/四库别集/贞一斋稿_page5.html"
  },
  {
    "name": "贞一斋稿_page6",
    "url": "集藏/四库别集/贞一斋稿_page6.html"
  },
  {
    "name": "贞白遗稿_page1",
    "url": "集藏/四库别集/贞白遗稿_page1.html"
  },
  {
    "name": "贞白遗稿_page10",
    "url": "集藏/四库别集/贞白遗稿_page10.html"
  },
  {
    "name": "贞白遗稿_page11",
    "url": "集藏/四库别集/贞白遗稿_page11.html"
  },
  {
    "name": "贞白遗稿_page12",
    "url": "集藏/四库别集/贞白遗稿_page12.html"
  },
  {
    "name": "贞白遗稿_page13",
    "url": "集藏/四库别集/贞白遗稿_page13.html"
  },
  {
    "name": "贞白遗稿_page14",
    "url": "集藏/四库别集/贞白遗稿_page14.html"
  },
  {
    "name": "贞白遗稿_page15",
    "url": "集藏/四库别集/贞白遗稿_page15.html"
  },
  {
    "name": "贞白遗稿_page2",
    "url": "集藏/四库别集/贞白遗稿_page2.html"
  },
  {
    "name": "贞白遗稿_page3",
    "url": "集藏/四库别集/贞白遗稿_page3.html"
  },
  {
    "name": "贞白遗稿_page4",
    "url": "集藏/四库别集/贞白遗稿_page4.html"
  },
  {
    "name": "贞白遗稿_page5",
    "url": "集藏/四库别集/贞白遗稿_page5.html"
  },
  {
    "name": "贞白遗稿_page6",
    "url": "集藏/四库别集/贞白遗稿_page6.html"
  },
  {
    "name": "贞白遗稿_page7",
    "url": "集藏/四库别集/贞白遗稿_page7.html"
  },
  {
    "name": "贞白遗稿_page8",
    "url": "集藏/四库别集/贞白遗稿_page8.html"
  },
  {
    "name": "贞白遗稿_page9",
    "url": "集藏/四库别集/贞白遗稿_page9.html"
  },
  {
    "name": "贞素斋集_page1",
    "url": "集藏/四库别集/贞素斋集_page1.html"
  },
  {
    "name": "贞素斋集_page10",
    "url": "集藏/四库别集/贞素斋集_page10.html"
  },
  {
    "name": "贞素斋集_page11",
    "url": "集藏/四库别集/贞素斋集_page11.html"
  },
  {
    "name": "贞素斋集_page12",
    "url": "集藏/四库别集/贞素斋集_page12.html"
  },
  {
    "name": "贞素斋集_page13",
    "url": "集藏/四库别集/贞素斋集_page13.html"
  },
  {
    "name": "贞素斋集_page14",
    "url": "集藏/四库别集/贞素斋集_page14.html"
  },
  {
    "name": "贞素斋集_page15",
    "url": "集藏/四库别集/贞素斋集_page15.html"
  },
  {
    "name": "贞素斋集_page2",
    "url": "集藏/四库别集/贞素斋集_page2.html"
  },
  {
    "name": "贞素斋集_page3",
    "url": "集藏/四库别集/贞素斋集_page3.html"
  },
  {
    "name": "贞素斋集_page4",
    "url": "集藏/四库别集/贞素斋集_page4.html"
  },
  {
    "name": "贞素斋集_page5",
    "url": "集藏/四库别集/贞素斋集_page5.html"
  },
  {
    "name": "贞素斋集_page6",
    "url": "集藏/四库别集/贞素斋集_page6.html"
  },
  {
    "name": "贞素斋集_page7",
    "url": "集藏/四库别集/贞素斋集_page7.html"
  },
  {
    "name": "贞素斋集_page8",
    "url": "集藏/四库别集/贞素斋集_page8.html"
  },
  {
    "name": "贞素斋集_page9",
    "url": "集藏/四库别集/贞素斋集_page9.html"
  },
  {
    "name": "贵耳集_page1",
    "url": "集藏/四库别集/贵耳集_page1.html"
  },
  {
    "name": "贵耳集_page2",
    "url": "集藏/四库别集/贵耳集_page2.html"
  },
  {
    "name": "贵耳集_page3",
    "url": "集藏/四库别集/贵耳集_page3.html"
  },
  {
    "name": "贵耳集_page4",
    "url": "集藏/四库别集/贵耳集_page4.html"
  },
  {
    "name": "贵耳集_page5",
    "url": "集藏/四库别集/贵耳集_page5.html"
  },
  {
    "name": "贵耳集_page6",
    "url": "集藏/四库别集/贵耳集_page6.html"
  },
  {
    "name": "贾岛集_page1",
    "url": "集藏/四库别集/贾岛集_page1.html"
  },
  {
    "name": "贾岛集_page10",
    "url": "集藏/四库别集/贾岛集_page10.html"
  },
  {
    "name": "贾岛集_page11",
    "url": "集藏/四库别集/贾岛集_page11.html"
  },
  {
    "name": "贾岛集_page12",
    "url": "集藏/四库别集/贾岛集_page12.html"
  },
  {
    "name": "贾岛集_page13",
    "url": "集藏/四库别集/贾岛集_page13.html"
  },
  {
    "name": "贾岛集_page14",
    "url": "集藏/四库别集/贾岛集_page14.html"
  },
  {
    "name": "贾岛集_page15",
    "url": "集藏/四库别集/贾岛集_page15.html"
  },
  {
    "name": "贾岛集_page16",
    "url": "集藏/四库别集/贾岛集_page16.html"
  },
  {
    "name": "贾岛集_page17",
    "url": "集藏/四库别集/贾岛集_page17.html"
  },
  {
    "name": "贾岛集_page18",
    "url": "集藏/四库别集/贾岛集_page18.html"
  },
  {
    "name": "贾岛集_page2",
    "url": "集藏/四库别集/贾岛集_page2.html"
  },
  {
    "name": "贾岛集_page3",
    "url": "集藏/四库别集/贾岛集_page3.html"
  },
  {
    "name": "贾岛集_page4",
    "url": "集藏/四库别集/贾岛集_page4.html"
  },
  {
    "name": "贾岛集_page5",
    "url": "集藏/四库别集/贾岛集_page5.html"
  },
  {
    "name": "贾岛集_page6",
    "url": "集藏/四库别集/贾岛集_page6.html"
  },
  {
    "name": "贾岛集_page7",
    "url": "集藏/四库别集/贾岛集_page7.html"
  },
  {
    "name": "贾岛集_page8",
    "url": "集藏/四库别集/贾岛集_page8.html"
  },
  {
    "name": "贾岛集_page9",
    "url": "集藏/四库别集/贾岛集_page9.html"
  },
  {
    "name": "资暇集_page1",
    "url": "集藏/四库别集/资暇集_page1.html"
  },
  {
    "name": "资暇集_page2",
    "url": "集藏/四库别集/资暇集_page2.html"
  },
  {
    "name": "资暇集_page3",
    "url": "集藏/四库别集/资暇集_page3.html"
  },
  {
    "name": "资暇集_page4",
    "url": "集藏/四库别集/资暇集_page4.html"
  },
  {
    "name": "赤崁集_page1",
    "url": "集藏/四库别集/赤崁集_page1.html"
  },
  {
    "name": "赤崁集_page10",
    "url": "集藏/四库别集/赤崁集_page10.html"
  },
  {
    "name": "赤崁集_page11",
    "url": "集藏/四库别集/赤崁集_page11.html"
  },
  {
    "name": "赤崁集_page12",
    "url": "集藏/四库别集/赤崁集_page12.html"
  },
  {
    "name": "赤崁集_page13",
    "url": "集藏/四库别集/赤崁集_page13.html"
  },
  {
    "name": "赤崁集_page14",
    "url": "集藏/四库别集/赤崁集_page14.html"
  },
  {
    "name": "赤崁集_page2",
    "url": "集藏/四库别集/赤崁集_page2.html"
  },
  {
    "name": "赤崁集_page3",
    "url": "集藏/四库别集/赤崁集_page3.html"
  },
  {
    "name": "赤崁集_page4",
    "url": "集藏/四库别集/赤崁集_page4.html"
  },
  {
    "name": "赤崁集_page5",
    "url": "集藏/四库别集/赤崁集_page5.html"
  },
  {
    "name": "赤崁集_page6",
    "url": "集藏/四库别集/赤崁集_page6.html"
  },
  {
    "name": "赤崁集_page7",
    "url": "集藏/四库别集/赤崁集_page7.html"
  },
  {
    "name": "赤崁集_page8",
    "url": "集藏/四库别集/赤崁集_page8.html"
  },
  {
    "name": "赤崁集_page9",
    "url": "集藏/四库别集/赤崁集_page9.html"
  },
  {
    "name": "赵考古文集_page1",
    "url": "集藏/四库别集/赵考古文集_page1.html"
  },
  {
    "name": "赵考古文集_page2",
    "url": "集藏/四库别集/赵考古文集_page2.html"
  },
  {
    "name": "赵考古文集_page3",
    "url": "集藏/四库别集/赵考古文集_page3.html"
  },
  {
    "name": "赵考古文集_page4",
    "url": "集藏/四库别集/赵考古文集_page4.html"
  },
  {
    "name": "跨鼇集_page1",
    "url": "集藏/四库别集/跨鼇集_page1.html"
  },
  {
    "name": "跨鼇集_page10",
    "url": "集藏/四库别集/跨鼇集_page10.html"
  },
  {
    "name": "跨鼇集_page11",
    "url": "集藏/四库别集/跨鼇集_page11.html"
  },
  {
    "name": "跨鼇集_page12",
    "url": "集藏/四库别集/跨鼇集_page12.html"
  },
  {
    "name": "跨鼇集_page13",
    "url": "集藏/四库别集/跨鼇集_page13.html"
  },
  {
    "name": "跨鼇集_page14",
    "url": "集藏/四库别集/跨鼇集_page14.html"
  },
  {
    "name": "跨鼇集_page15",
    "url": "集藏/四库别集/跨鼇集_page15.html"
  },
  {
    "name": "跨鼇集_page16",
    "url": "集藏/四库别集/跨鼇集_page16.html"
  },
  {
    "name": "跨鼇集_page17",
    "url": "集藏/四库别集/跨鼇集_page17.html"
  },
  {
    "name": "跨鼇集_page18",
    "url": "集藏/四库别集/跨鼇集_page18.html"
  },
  {
    "name": "跨鼇集_page2",
    "url": "集藏/四库别集/跨鼇集_page2.html"
  },
  {
    "name": "跨鼇集_page3",
    "url": "集藏/四库别集/跨鼇集_page3.html"
  },
  {
    "name": "跨鼇集_page4",
    "url": "集藏/四库别集/跨鼇集_page4.html"
  },
  {
    "name": "跨鼇集_page5",
    "url": "集藏/四库别集/跨鼇集_page5.html"
  },
  {
    "name": "跨鼇集_page6",
    "url": "集藏/四库别集/跨鼇集_page6.html"
  },
  {
    "name": "跨鼇集_page7",
    "url": "集藏/四库别集/跨鼇集_page7.html"
  },
  {
    "name": "跨鼇集_page8",
    "url": "集藏/四库别集/跨鼇集_page8.html"
  },
  {
    "name": "跨鼇集_page9",
    "url": "集藏/四库别集/跨鼇集_page9.html"
  },
  {
    "name": "运甓漫稿_page1",
    "url": "集藏/四库别集/运甓漫稿_page1.html"
  },
  {
    "name": "运甓漫稿_page10",
    "url": "集藏/四库别集/运甓漫稿_page10.html"
  },
  {
    "name": "运甓漫稿_page11",
    "url": "集藏/四库别集/运甓漫稿_page11.html"
  },
  {
    "name": "运甓漫稿_page12",
    "url": "集藏/四库别集/运甓漫稿_page12.html"
  },
  {
    "name": "运甓漫稿_page13",
    "url": "集藏/四库别集/运甓漫稿_page13.html"
  },
  {
    "name": "运甓漫稿_page14",
    "url": "集藏/四库别集/运甓漫稿_page14.html"
  },
  {
    "name": "运甓漫稿_page15",
    "url": "集藏/四库别集/运甓漫稿_page15.html"
  },
  {
    "name": "运甓漫稿_page16",
    "url": "集藏/四库别集/运甓漫稿_page16.html"
  },
  {
    "name": "运甓漫稿_page17",
    "url": "集藏/四库别集/运甓漫稿_page17.html"
  },
  {
    "name": "运甓漫稿_page18",
    "url": "集藏/四库别集/运甓漫稿_page18.html"
  },
  {
    "name": "运甓漫稿_page19",
    "url": "集藏/四库别集/运甓漫稿_page19.html"
  },
  {
    "name": "运甓漫稿_page2",
    "url": "集藏/四库别集/运甓漫稿_page2.html"
  },
  {
    "name": "运甓漫稿_page20",
    "url": "集藏/四库别集/运甓漫稿_page20.html"
  },
  {
    "name": "运甓漫稿_page21",
    "url": "集藏/四库别集/运甓漫稿_page21.html"
  },
  {
    "name": "运甓漫稿_page22",
    "url": "集藏/四库别集/运甓漫稿_page22.html"
  },
  {
    "name": "运甓漫稿_page23",
    "url": "集藏/四库别集/运甓漫稿_page23.html"
  },
  {
    "name": "运甓漫稿_page24",
    "url": "集藏/四库别集/运甓漫稿_page24.html"
  },
  {
    "name": "运甓漫稿_page25",
    "url": "集藏/四库别集/运甓漫稿_page25.html"
  },
  {
    "name": "运甓漫稿_page26",
    "url": "集藏/四库别集/运甓漫稿_page26.html"
  },
  {
    "name": "运甓漫稿_page3",
    "url": "集藏/四库别集/运甓漫稿_page3.html"
  },
  {
    "name": "运甓漫稿_page4",
    "url": "集藏/四库别集/运甓漫稿_page4.html"
  },
  {
    "name": "运甓漫稿_page5",
    "url": "集藏/四库别集/运甓漫稿_page5.html"
  },
  {
    "name": "运甓漫稿_page6",
    "url": "集藏/四库别集/运甓漫稿_page6.html"
  },
  {
    "name": "运甓漫稿_page7",
    "url": "集藏/四库别集/运甓漫稿_page7.html"
  },
  {
    "name": "运甓漫稿_page8",
    "url": "集藏/四库别集/运甓漫稿_page8.html"
  },
  {
    "name": "运甓漫稿_page9",
    "url": "集藏/四库别集/运甓漫稿_page9.html"
  },
  {
    "name": "近光集_page1",
    "url": "集藏/四库别集/近光集_page1.html"
  },
  {
    "name": "近光集_page2",
    "url": "集藏/四库别集/近光集_page2.html"
  },
  {
    "name": "近光集_page3",
    "url": "集藏/四库别集/近光集_page3.html"
  },
  {
    "name": "近光集_page4",
    "url": "集藏/四库别集/近光集_page4.html"
  },
  {
    "name": "近光集_page5",
    "url": "集藏/四库别集/近光集_page5.html"
  },
  {
    "name": "近光集_page6",
    "url": "集藏/四库别集/近光集_page6.html"
  },
  {
    "name": "近光集_page7",
    "url": "集藏/四库别集/近光集_page7.html"
  },
  {
    "name": "近光集_page8",
    "url": "集藏/四库别集/近光集_page8.html"
  },
  {
    "name": "近光集_page9",
    "url": "集藏/四库别集/近光集_page9.html"
  },
  {
    "name": "近光集扈从集_page1",
    "url": "集藏/四库别集/近光集扈从集_page1.html"
  },
  {
    "name": "近光集扈从集_page2",
    "url": "集藏/四库别集/近光集扈从集_page2.html"
  },
  {
    "name": "近光集扈从集_page3",
    "url": "集藏/四库别集/近光集扈从集_page3.html"
  },
  {
    "name": "近光集扈从集_page4",
    "url": "集藏/四库别集/近光集扈从集_page4.html"
  },
  {
    "name": "近光集扈从集_page5",
    "url": "集藏/四库别集/近光集扈从集_page5.html"
  },
  {
    "name": "还山遗稿_page1",
    "url": "集藏/四库别集/还山遗稿_page1.html"
  },
  {
    "name": "还山遗稿_page2",
    "url": "集藏/四库别集/还山遗稿_page2.html"
  },
  {
    "name": "还山遗稿_page3",
    "url": "集藏/四库别集/还山遗稿_page3.html"
  },
  {
    "name": "还山遗稿_page4",
    "url": "集藏/四库别集/还山遗稿_page4.html"
  },
  {
    "name": "还山遗稿_page5",
    "url": "集藏/四库别集/还山遗稿_page5.html"
  },
  {
    "name": "还山遗稿_page6",
    "url": "集藏/四库别集/还山遗稿_page6.html"
  },
  {
    "name": "迪功集_page1",
    "url": "集藏/四库别集/迪功集_page1.html"
  },
  {
    "name": "迪功集_page2",
    "url": "集藏/四库别集/迪功集_page2.html"
  },
  {
    "name": "迪功集_page3",
    "url": "集藏/四库别集/迪功集_page3.html"
  },
  {
    "name": "迪功集_page4",
    "url": "集藏/四库别集/迪功集_page4.html"
  },
  {
    "name": "迪功集_page5",
    "url": "集藏/四库别集/迪功集_page5.html"
  },
  {
    "name": "迪功集_page6",
    "url": "集藏/四库别集/迪功集_page6.html"
  },
  {
    "name": "迪功集_page7",
    "url": "集藏/四库别集/迪功集_page7.html"
  },
  {
    "name": "迪功集_page8",
    "url": "集藏/四库别集/迪功集_page8.html"
  },
  {
    "name": "迪功集_page9",
    "url": "集藏/四库别集/迪功集_page9.html"
  },
  {
    "name": "追昔游集_page1",
    "url": "集藏/四库别集/追昔游集_page1.html"
  },
  {
    "name": "追昔游集_page2",
    "url": "集藏/四库别集/追昔游集_page2.html"
  },
  {
    "name": "追昔游集_page3",
    "url": "集藏/四库别集/追昔游集_page3.html"
  },
  {
    "name": "追昔游集_page4",
    "url": "集藏/四库别集/追昔游集_page4.html"
  },
  {
    "name": "逊志斋集_page1",
    "url": "集藏/四库别集/逊志斋集_page1.html"
  },
  {
    "name": "逊志斋集_page10",
    "url": "集藏/四库别集/逊志斋集_page10.html"
  },
  {
    "name": "逊志斋集_page11",
    "url": "集藏/四库别集/逊志斋集_page11.html"
  },
  {
    "name": "逊志斋集_page12",
    "url": "集藏/四库别集/逊志斋集_page12.html"
  },
  {
    "name": "逊志斋集_page13",
    "url": "集藏/四库别集/逊志斋集_page13.html"
  },
  {
    "name": "逊志斋集_page14",
    "url": "集藏/四库别集/逊志斋集_page14.html"
  },
  {
    "name": "逊志斋集_page15",
    "url": "集藏/四库别集/逊志斋集_page15.html"
  },
  {
    "name": "逊志斋集_page16",
    "url": "集藏/四库别集/逊志斋集_page16.html"
  },
  {
    "name": "逊志斋集_page17",
    "url": "集藏/四库别集/逊志斋集_page17.html"
  },
  {
    "name": "逊志斋集_page18",
    "url": "集藏/四库别集/逊志斋集_page18.html"
  },
  {
    "name": "逊志斋集_page19",
    "url": "集藏/四库别集/逊志斋集_page19.html"
  },
  {
    "name": "逊志斋集_page2",
    "url": "集藏/四库别集/逊志斋集_page2.html"
  },
  {
    "name": "逊志斋集_page20",
    "url": "集藏/四库别集/逊志斋集_page20.html"
  },
  {
    "name": "逊志斋集_page21",
    "url": "集藏/四库别集/逊志斋集_page21.html"
  },
  {
    "name": "逊志斋集_page22",
    "url": "集藏/四库别集/逊志斋集_page22.html"
  },
  {
    "name": "逊志斋集_page23",
    "url": "集藏/四库别集/逊志斋集_page23.html"
  },
  {
    "name": "逊志斋集_page24",
    "url": "集藏/四库别集/逊志斋集_page24.html"
  },
  {
    "name": "逊志斋集_page25",
    "url": "集藏/四库别集/逊志斋集_page25.html"
  },
  {
    "name": "逊志斋集_page26",
    "url": "集藏/四库别集/逊志斋集_page26.html"
  },
  {
    "name": "逊志斋集_page27",
    "url": "集藏/四库别集/逊志斋集_page27.html"
  },
  {
    "name": "逊志斋集_page28",
    "url": "集藏/四库别集/逊志斋集_page28.html"
  },
  {
    "name": "逊志斋集_page3",
    "url": "集藏/四库别集/逊志斋集_page3.html"
  },
  {
    "name": "逊志斋集_page4",
    "url": "集藏/四库别集/逊志斋集_page4.html"
  },
  {
    "name": "逊志斋集_page5",
    "url": "集藏/四库别集/逊志斋集_page5.html"
  },
  {
    "name": "逊志斋集_page6",
    "url": "集藏/四库别集/逊志斋集_page6.html"
  },
  {
    "name": "逊志斋集_page7",
    "url": "集藏/四库别集/逊志斋集_page7.html"
  },
  {
    "name": "逊志斋集_page8",
    "url": "集藏/四库别集/逊志斋集_page8.html"
  },
  {
    "name": "逊志斋集_page9",
    "url": "集藏/四库别集/逊志斋集_page9.html"
  },
  {
    "name": "逍遥集_page1",
    "url": "集藏/四库别集/逍遥集_page1.html"
  },
  {
    "name": "逍遥集_page2",
    "url": "集藏/四库别集/逍遥集_page2.html"
  },
  {
    "name": "道乡集_page1",
    "url": "集藏/四库别集/道乡集_page1.html"
  },
  {
    "name": "道乡集_page10",
    "url": "集藏/四库别集/道乡集_page10.html"
  },
  {
    "name": "道乡集_page11",
    "url": "集藏/四库别集/道乡集_page11.html"
  },
  {
    "name": "道乡集_page12",
    "url": "集藏/四库别集/道乡集_page12.html"
  },
  {
    "name": "道乡集_page13",
    "url": "集藏/四库别集/道乡集_page13.html"
  },
  {
    "name": "道乡集_page14",
    "url": "集藏/四库别集/道乡集_page14.html"
  },
  {
    "name": "道乡集_page15",
    "url": "集藏/四库别集/道乡集_page15.html"
  },
  {
    "name": "道乡集_page16",
    "url": "集藏/四库别集/道乡集_page16.html"
  },
  {
    "name": "道乡集_page17",
    "url": "集藏/四库别集/道乡集_page17.html"
  },
  {
    "name": "道乡集_page18",
    "url": "集藏/四库别集/道乡集_page18.html"
  },
  {
    "name": "道乡集_page19",
    "url": "集藏/四库别集/道乡集_page19.html"
  },
  {
    "name": "道乡集_page2",
    "url": "集藏/四库别集/道乡集_page2.html"
  },
  {
    "name": "道乡集_page20",
    "url": "集藏/四库别集/道乡集_page20.html"
  },
  {
    "name": "道乡集_page21",
    "url": "集藏/四库别集/道乡集_page21.html"
  },
  {
    "name": "道乡集_page22",
    "url": "集藏/四库别集/道乡集_page22.html"
  },
  {
    "name": "道乡集_page23",
    "url": "集藏/四库别集/道乡集_page23.html"
  },
  {
    "name": "道乡集_page24",
    "url": "集藏/四库别集/道乡集_page24.html"
  },
  {
    "name": "道乡集_page25",
    "url": "集藏/四库别集/道乡集_page25.html"
  },
  {
    "name": "道乡集_page26",
    "url": "集藏/四库别集/道乡集_page26.html"
  },
  {
    "name": "道乡集_page27",
    "url": "集藏/四库别集/道乡集_page27.html"
  },
  {
    "name": "道乡集_page28",
    "url": "集藏/四库别集/道乡集_page28.html"
  },
  {
    "name": "道乡集_page29",
    "url": "集藏/四库别集/道乡集_page29.html"
  },
  {
    "name": "道乡集_page3",
    "url": "集藏/四库别集/道乡集_page3.html"
  },
  {
    "name": "道乡集_page30",
    "url": "集藏/四库别集/道乡集_page30.html"
  },
  {
    "name": "道乡集_page31",
    "url": "集藏/四库别集/道乡集_page31.html"
  },
  {
    "name": "道乡集_page32",
    "url": "集藏/四库别集/道乡集_page32.html"
  },
  {
    "name": "道乡集_page33",
    "url": "集藏/四库别集/道乡集_page33.html"
  },
  {
    "name": "道乡集_page4",
    "url": "集藏/四库别集/道乡集_page4.html"
  },
  {
    "name": "道乡集_page5",
    "url": "集藏/四库别集/道乡集_page5.html"
  },
  {
    "name": "道乡集_page6",
    "url": "集藏/四库别集/道乡集_page6.html"
  },
  {
    "name": "道乡集_page7",
    "url": "集藏/四库别集/道乡集_page7.html"
  },
  {
    "name": "道乡集_page8",
    "url": "集藏/四库别集/道乡集_page8.html"
  },
  {
    "name": "道乡集_page9",
    "url": "集藏/四库别集/道乡集_page9.html"
  },
  {
    "name": "道园学古录_page1",
    "url": "集藏/四库别集/道园学古录_page1.html"
  },
  {
    "name": "道园学古录_page10",
    "url": "集藏/四库别集/道园学古录_page10.html"
  },
  {
    "name": "道园学古录_page11",
    "url": "集藏/四库别集/道园学古录_page11.html"
  },
  {
    "name": "道园学古录_page12",
    "url": "集藏/四库别集/道园学古录_page12.html"
  }
]